[
  {
    "Iteration":0,
    "Value":-11.5135135135,
    "Agent":"C2D"
  },
  {
    "Iteration":1,
    "Value":-14.6527777778,
    "Agent":"C2D"
  },
  {
    "Iteration":2,
    "Value":-14.4027777778,
    "Agent":"C2D"
  },
  {
    "Iteration":3,
    "Value":-14.7945205479,
    "Agent":"C2D"
  },
  {
    "Iteration":4,
    "Value":-14.5138888889,
    "Agent":"C2D"
  },
  {
    "Iteration":5,
    "Value":-14.8219178082,
    "Agent":"C2D"
  },
  {
    "Iteration":6,
    "Value":-14.3611111111,
    "Agent":"C2D"
  },
  {
    "Iteration":7,
    "Value":-14.9166666667,
    "Agent":"C2D"
  },
  {
    "Iteration":8,
    "Value":-15.1527777778,
    "Agent":"C2D"
  },
  {
    "Iteration":9,
    "Value":-15.6388888889,
    "Agent":"C2D"
  },
  {
    "Iteration":10,
    "Value":-15.7042253521,
    "Agent":"C2D"
  },
  {
    "Iteration":11,
    "Value":-16.2816901408,
    "Agent":"C2D"
  },
  {
    "Iteration":12,
    "Value":-15.7222222222,
    "Agent":"C2D"
  },
  {
    "Iteration":13,
    "Value":-15.75,
    "Agent":"C2D"
  },
  {
    "Iteration":14,
    "Value":-16.125,
    "Agent":"C2D"
  },
  {
    "Iteration":15,
    "Value":-15.5555555556,
    "Agent":"C2D"
  },
  {
    "Iteration":16,
    "Value":-14.6388888889,
    "Agent":"C2D"
  },
  {
    "Iteration":17,
    "Value":-16.2535211268,
    "Agent":"C2D"
  },
  {
    "Iteration":18,
    "Value":-15.661971831,
    "Agent":"C2D"
  },
  {
    "Iteration":19,
    "Value":-15.1111111111,
    "Agent":"C2D"
  },
  {
    "Iteration":20,
    "Value":-14.4246575342,
    "Agent":"C2D"
  },
  {
    "Iteration":21,
    "Value":-14.6901408451,
    "Agent":"C2D"
  },
  {
    "Iteration":22,
    "Value":-12.4383561644,
    "Agent":"C2D"
  },
  {
    "Iteration":23,
    "Value":-13.875,
    "Agent":"C2D"
  },
  {
    "Iteration":24,
    "Value":-15.2253521127,
    "Agent":"C2D"
  },
  {
    "Iteration":25,
    "Value":-14.7361111111,
    "Agent":"C2D"
  },
  {
    "Iteration":26,
    "Value":-14.25,
    "Agent":"C2D"
  },
  {
    "Iteration":27,
    "Value":-15.3194444444,
    "Agent":"C2D"
  },
  {
    "Iteration":28,
    "Value":-16.1111111111,
    "Agent":"C2D"
  },
  {
    "Iteration":29,
    "Value":-15.3611111111,
    "Agent":"C2D"
  },
  {
    "Iteration":30,
    "Value":-13.7567567568,
    "Agent":"C2D"
  },
  {
    "Iteration":31,
    "Value":-13.8904109589,
    "Agent":"C2D"
  },
  {
    "Iteration":32,
    "Value":-12.6486486486,
    "Agent":"C2D"
  },
  {
    "Iteration":33,
    "Value":-13.472972973,
    "Agent":"C2D"
  },
  {
    "Iteration":34,
    "Value":-11.16,
    "Agent":"C2D"
  },
  {
    "Iteration":35,
    "Value":-11.9066666667,
    "Agent":"C2D"
  },
  {
    "Iteration":36,
    "Value":-12.3918918919,
    "Agent":"C2D"
  },
  {
    "Iteration":37,
    "Value":-12.6486486486,
    "Agent":"C2D"
  },
  {
    "Iteration":38,
    "Value":-11.84,
    "Agent":"C2D"
  },
  {
    "Iteration":39,
    "Value":-12.12,
    "Agent":"C2D"
  },
  {
    "Iteration":40,
    "Value":-12.6756756757,
    "Agent":"C2D"
  },
  {
    "Iteration":41,
    "Value":-11.6533333333,
    "Agent":"C2D"
  },
  {
    "Iteration":42,
    "Value":-12.972972973,
    "Agent":"C2D"
  },
  {
    "Iteration":43,
    "Value":-11.7297297297,
    "Agent":"C2D"
  },
  {
    "Iteration":44,
    "Value":-11.8378378378,
    "Agent":"C2D"
  },
  {
    "Iteration":45,
    "Value":-11.2763157895,
    "Agent":"C2D"
  },
  {
    "Iteration":46,
    "Value":-10.8421052632,
    "Agent":"C2D"
  },
  {
    "Iteration":47,
    "Value":-9.9736842105,
    "Agent":"C2D"
  },
  {
    "Iteration":48,
    "Value":-10.1973684211,
    "Agent":"C2D"
  },
  {
    "Iteration":49,
    "Value":-8.6493506494,
    "Agent":"C2D"
  },
  {
    "Iteration":50,
    "Value":-8.4545454545,
    "Agent":"C2D"
  },
  {
    "Iteration":51,
    "Value":-8.8051948052,
    "Agent":"C2D"
  },
  {
    "Iteration":52,
    "Value":-8.8684210526,
    "Agent":"C2D"
  },
  {
    "Iteration":53,
    "Value":-9.3333333333,
    "Agent":"C2D"
  },
  {
    "Iteration":54,
    "Value":-7.8266666667,
    "Agent":"C2D"
  },
  {
    "Iteration":55,
    "Value":-7.4415584416,
    "Agent":"C2D"
  },
  {
    "Iteration":56,
    "Value":-7.5810810811,
    "Agent":"C2D"
  },
  {
    "Iteration":57,
    "Value":-7.1486486486,
    "Agent":"C2D"
  },
  {
    "Iteration":58,
    "Value":-7.0921052632,
    "Agent":"C2D"
  },
  {
    "Iteration":59,
    "Value":-7.1081081081,
    "Agent":"C2D"
  },
  {
    "Iteration":60,
    "Value":-6.3157894737,
    "Agent":"C2D"
  },
  {
    "Iteration":61,
    "Value":-5.7763157895,
    "Agent":"C2D"
  },
  {
    "Iteration":62,
    "Value":-6.16,
    "Agent":"C2D"
  },
  {
    "Iteration":63,
    "Value":-6.5333333333,
    "Agent":"C2D"
  },
  {
    "Iteration":64,
    "Value":-6.5789473684,
    "Agent":"C2D"
  },
  {
    "Iteration":65,
    "Value":-6.5263157895,
    "Agent":"C2D"
  },
  {
    "Iteration":66,
    "Value":-5.9078947368,
    "Agent":"C2D"
  },
  {
    "Iteration":67,
    "Value":-5.7662337662,
    "Agent":"C2D"
  },
  {
    "Iteration":68,
    "Value":-5.6052631579,
    "Agent":"C2D"
  },
  {
    "Iteration":69,
    "Value":-5.8947368421,
    "Agent":"C2D"
  },
  {
    "Iteration":70,
    "Value":-5.2,
    "Agent":"C2D"
  },
  {
    "Iteration":71,
    "Value":-5.4189189189,
    "Agent":"C2D"
  },
  {
    "Iteration":72,
    "Value":-5.1315789474,
    "Agent":"C2D"
  },
  {
    "Iteration":73,
    "Value":-5.1756756757,
    "Agent":"C2D"
  },
  {
    "Iteration":74,
    "Value":-5.2631578947,
    "Agent":"C2D"
  },
  {
    "Iteration":75,
    "Value":-5.2027027027,
    "Agent":"C2D"
  },
  {
    "Iteration":76,
    "Value":-4.5733333333,
    "Agent":"C2D"
  },
  {
    "Iteration":77,
    "Value":-4.8666666667,
    "Agent":"C2D"
  },
  {
    "Iteration":78,
    "Value":-5.6891891892,
    "Agent":"C2D"
  },
  {
    "Iteration":79,
    "Value":-6.0133333333,
    "Agent":"C2D"
  },
  {
    "Iteration":80,
    "Value":-5.1756756757,
    "Agent":"C2D"
  },
  {
    "Iteration":81,
    "Value":-5.1891891892,
    "Agent":"C2D"
  },
  {
    "Iteration":82,
    "Value":-5.1621621622,
    "Agent":"C2D"
  },
  {
    "Iteration":83,
    "Value":-5.1710526316,
    "Agent":"C2D"
  },
  {
    "Iteration":84,
    "Value":-5.6351351351,
    "Agent":"C2D"
  },
  {
    "Iteration":85,
    "Value":-6.3888888889,
    "Agent":"C2D"
  },
  {
    "Iteration":86,
    "Value":-6.0821917808,
    "Agent":"C2D"
  },
  {
    "Iteration":87,
    "Value":-5.2432432432,
    "Agent":"C2D"
  },
  {
    "Iteration":88,
    "Value":-4.8378378378,
    "Agent":"C2D"
  },
  {
    "Iteration":89,
    "Value":-4.7027027027,
    "Agent":"C2D"
  },
  {
    "Iteration":90,
    "Value":-5.6081081081,
    "Agent":"C2D"
  },
  {
    "Iteration":91,
    "Value":-5.7361111111,
    "Agent":"C2D"
  },
  {
    "Iteration":92,
    "Value":-5.6575342466,
    "Agent":"C2D"
  },
  {
    "Iteration":93,
    "Value":-5.027027027,
    "Agent":"C2D"
  },
  {
    "Iteration":94,
    "Value":-4.472972973,
    "Agent":"C2D"
  },
  {
    "Iteration":95,
    "Value":-5.8378378378,
    "Agent":"C2D"
  },
  {
    "Iteration":96,
    "Value":-5.7297297297,
    "Agent":"C2D"
  },
  {
    "Iteration":97,
    "Value":-5.4109589041,
    "Agent":"C2D"
  },
  {
    "Iteration":98,
    "Value":-5.301369863,
    "Agent":"C2D"
  },
  {
    "Iteration":99,
    "Value":-6.4657534247,
    "Agent":"C2D"
  },
  {
    "Iteration":100,
    "Value":-5.472972973,
    "Agent":"C2D"
  },
  {
    "Iteration":101,
    "Value":-6.1805555556,
    "Agent":"C2D"
  },
  {
    "Iteration":102,
    "Value":-5.9589041096,
    "Agent":"C2D"
  },
  {
    "Iteration":103,
    "Value":-5.3287671233,
    "Agent":"C2D"
  },
  {
    "Iteration":104,
    "Value":-6.2876712329,
    "Agent":"C2D"
  },
  {
    "Iteration":105,
    "Value":-5.1486486486,
    "Agent":"C2D"
  },
  {
    "Iteration":106,
    "Value":-5.125,
    "Agent":"C2D"
  },
  {
    "Iteration":107,
    "Value":-6.5555555556,
    "Agent":"C2D"
  },
  {
    "Iteration":108,
    "Value":-6.2361111111,
    "Agent":"C2D"
  },
  {
    "Iteration":109,
    "Value":-5.397260274,
    "Agent":"C2D"
  },
  {
    "Iteration":110,
    "Value":-6.4109589041,
    "Agent":"C2D"
  },
  {
    "Iteration":111,
    "Value":-5.2876712329,
    "Agent":"C2D"
  },
  {
    "Iteration":112,
    "Value":-5.1081081081,
    "Agent":"C2D"
  },
  {
    "Iteration":113,
    "Value":-6.2054794521,
    "Agent":"C2D"
  },
  {
    "Iteration":114,
    "Value":-6.7808219178,
    "Agent":"C2D"
  },
  {
    "Iteration":115,
    "Value":-6.4109589041,
    "Agent":"C2D"
  },
  {
    "Iteration":116,
    "Value":-6.5205479452,
    "Agent":"C2D"
  },
  {
    "Iteration":117,
    "Value":-6.0410958904,
    "Agent":"C2D"
  },
  {
    "Iteration":118,
    "Value":-5.7972972973,
    "Agent":"C2D"
  },
  {
    "Iteration":119,
    "Value":-5.375,
    "Agent":"C2D"
  },
  {
    "Iteration":120,
    "Value":-5.8082191781,
    "Agent":"C2D"
  },
  {
    "Iteration":121,
    "Value":-6.0136986301,
    "Agent":"C2D"
  },
  {
    "Iteration":122,
    "Value":-5.9861111111,
    "Agent":"C2D"
  },
  {
    "Iteration":123,
    "Value":-5.5277777778,
    "Agent":"C2D"
  },
  {
    "Iteration":124,
    "Value":-6.875,
    "Agent":"C2D"
  },
  {
    "Iteration":125,
    "Value":-6.1917808219,
    "Agent":"C2D"
  },
  {
    "Iteration":126,
    "Value":-5.4027777778,
    "Agent":"C2D"
  },
  {
    "Iteration":127,
    "Value":-5.6438356164,
    "Agent":"C2D"
  },
  {
    "Iteration":128,
    "Value":-5.9027777778,
    "Agent":"C2D"
  },
  {
    "Iteration":129,
    "Value":-5.7746478873,
    "Agent":"C2D"
  },
  {
    "Iteration":130,
    "Value":-5.6111111111,
    "Agent":"C2D"
  },
  {
    "Iteration":131,
    "Value":-5.2394366197,
    "Agent":"C2D"
  },
  {
    "Iteration":132,
    "Value":-5.2285714286,
    "Agent":"C2D"
  },
  {
    "Iteration":133,
    "Value":-5.2571428571,
    "Agent":"C2D"
  },
  {
    "Iteration":134,
    "Value":-4.5277777778,
    "Agent":"C2D"
  },
  {
    "Iteration":135,
    "Value":-5.5915492958,
    "Agent":"C2D"
  },
  {
    "Iteration":136,
    "Value":-5.5,
    "Agent":"C2D"
  },
  {
    "Iteration":137,
    "Value":-6.3521126761,
    "Agent":"C2D"
  },
  {
    "Iteration":138,
    "Value":-5.875,
    "Agent":"C2D"
  },
  {
    "Iteration":139,
    "Value":-5.1690140845,
    "Agent":"C2D"
  },
  {
    "Iteration":140,
    "Value":-5.3333333333,
    "Agent":"C2D"
  },
  {
    "Iteration":141,
    "Value":-5.6438356164,
    "Agent":"C2D"
  },
  {
    "Iteration":142,
    "Value":-5.095890411,
    "Agent":"C2D"
  },
  {
    "Iteration":143,
    "Value":-5.095890411,
    "Agent":"C2D"
  },
  {
    "Iteration":144,
    "Value":-5.7183098592,
    "Agent":"C2D"
  },
  {
    "Iteration":145,
    "Value":-5.4861111111,
    "Agent":"C2D"
  },
  {
    "Iteration":146,
    "Value":-5.0138888889,
    "Agent":"C2D"
  },
  {
    "Iteration":147,
    "Value":-4.4507042254,
    "Agent":"C2D"
  },
  {
    "Iteration":148,
    "Value":-5.6849315068,
    "Agent":"C2D"
  },
  {
    "Iteration":149,
    "Value":-6.25,
    "Agent":"C2D"
  },
  {
    "Iteration":150,
    "Value":-7.0138888889,
    "Agent":"C2D"
  },
  {
    "Iteration":151,
    "Value":-5.5070422535,
    "Agent":"C2D"
  },
  {
    "Iteration":152,
    "Value":-5.7361111111,
    "Agent":"C2D"
  },
  {
    "Iteration":153,
    "Value":-5.985915493,
    "Agent":"C2D"
  },
  {
    "Iteration":154,
    "Value":-5.338028169,
    "Agent":"C2D"
  },
  {
    "Iteration":155,
    "Value":-5.5352112676,
    "Agent":"C2D"
  },
  {
    "Iteration":156,
    "Value":-6.2638888889,
    "Agent":"C2D"
  },
  {
    "Iteration":157,
    "Value":-6.1857142857,
    "Agent":"C2D"
  },
  {
    "Iteration":158,
    "Value":-6.4857142857,
    "Agent":"C2D"
  },
  {
    "Iteration":159,
    "Value":-4.9436619718,
    "Agent":"C2D"
  },
  {
    "Iteration":160,
    "Value":-5.9014084507,
    "Agent":"C2D"
  },
  {
    "Iteration":161,
    "Value":-5.0972222222,
    "Agent":"C2D"
  },
  {
    "Iteration":162,
    "Value":-5.2676056338,
    "Agent":"C2D"
  },
  {
    "Iteration":163,
    "Value":-4.7183098592,
    "Agent":"C2D"
  },
  {
    "Iteration":164,
    "Value":-5.8450704225,
    "Agent":"C2D"
  },
  {
    "Iteration":165,
    "Value":-5.1971830986,
    "Agent":"C2D"
  },
  {
    "Iteration":166,
    "Value":-5.0144927536,
    "Agent":"C2D"
  },
  {
    "Iteration":167,
    "Value":-5.5070422535,
    "Agent":"C2D"
  },
  {
    "Iteration":168,
    "Value":-5.9295774648,
    "Agent":"C2D"
  },
  {
    "Iteration":169,
    "Value":-5.9718309859,
    "Agent":"C2D"
  },
  {
    "Iteration":170,
    "Value":-4.6056338028,
    "Agent":"C2D"
  },
  {
    "Iteration":171,
    "Value":-6.5774647887,
    "Agent":"C2D"
  },
  {
    "Iteration":172,
    "Value":-5.6857142857,
    "Agent":"C2D"
  },
  {
    "Iteration":173,
    "Value":-5.1571428571,
    "Agent":"C2D"
  },
  {
    "Iteration":174,
    "Value":-5.2676056338,
    "Agent":"C2D"
  },
  {
    "Iteration":175,
    "Value":-5.4583333333,
    "Agent":"C2D"
  },
  {
    "Iteration":176,
    "Value":-5.5857142857,
    "Agent":"C2D"
  },
  {
    "Iteration":177,
    "Value":-5.7746478873,
    "Agent":"C2D"
  },
  {
    "Iteration":178,
    "Value":-6.4142857143,
    "Agent":"C2D"
  },
  {
    "Iteration":179,
    "Value":-5.0571428571,
    "Agent":"C2D"
  },
  {
    "Iteration":180,
    "Value":-5.6285714286,
    "Agent":"C2D"
  },
  {
    "Iteration":181,
    "Value":-6.5352112676,
    "Agent":"C2D"
  },
  {
    "Iteration":182,
    "Value":-6.1408450704,
    "Agent":"C2D"
  },
  {
    "Iteration":183,
    "Value":-5.8591549296,
    "Agent":"C2D"
  },
  {
    "Iteration":184,
    "Value":-5.0857142857,
    "Agent":"C2D"
  },
  {
    "Iteration":185,
    "Value":-6.3142857143,
    "Agent":"C2D"
  },
  {
    "Iteration":186,
    "Value":-5.6056338028,
    "Agent":"C2D"
  },
  {
    "Iteration":187,
    "Value":-4.9275362319,
    "Agent":"C2D"
  },
  {
    "Iteration":188,
    "Value":-5.4507042254,
    "Agent":"C2D"
  },
  {
    "Iteration":189,
    "Value":-5.5714285714,
    "Agent":"C2D"
  },
  {
    "Iteration":190,
    "Value":-5.8450704225,
    "Agent":"C2D"
  },
  {
    "Iteration":191,
    "Value":-5.7887323944,
    "Agent":"C2D"
  },
  {
    "Iteration":192,
    "Value":-4.9718309859,
    "Agent":"C2D"
  },
  {
    "Iteration":193,
    "Value":-5.1714285714,
    "Agent":"C2D"
  },
  {
    "Iteration":194,
    "Value":-5.9,
    "Agent":"C2D"
  },
  {
    "Iteration":195,
    "Value":-5.2571428571,
    "Agent":"C2D"
  },
  {
    "Iteration":196,
    "Value":-5.5479452055,
    "Agent":"C2D"
  },
  {
    "Iteration":197,
    "Value":-5.8028169014,
    "Agent":"C2D"
  },
  {
    "Iteration":198,
    "Value":-6.4861111111,
    "Agent":"C2D"
  },
  {
    "Iteration":199,
    "Value":-5.4,
    "Agent":"C2D"
  },
  {
    "Iteration":0,
    "Value":-11.7432432432,
    "Agent":"C2D"
  },
  {
    "Iteration":1,
    "Value":-15.2222222222,
    "Agent":"C2D"
  },
  {
    "Iteration":2,
    "Value":-15.0694444444,
    "Agent":"C2D"
  },
  {
    "Iteration":3,
    "Value":-15.6388888889,
    "Agent":"C2D"
  },
  {
    "Iteration":4,
    "Value":-15.0,
    "Agent":"C2D"
  },
  {
    "Iteration":5,
    "Value":-15.6805555556,
    "Agent":"C2D"
  },
  {
    "Iteration":6,
    "Value":-15.375,
    "Agent":"C2D"
  },
  {
    "Iteration":7,
    "Value":-14.8472222222,
    "Agent":"C2D"
  },
  {
    "Iteration":8,
    "Value":-14.0972222222,
    "Agent":"C2D"
  },
  {
    "Iteration":9,
    "Value":-16.2676056338,
    "Agent":"C2D"
  },
  {
    "Iteration":10,
    "Value":-16.1388888889,
    "Agent":"C2D"
  },
  {
    "Iteration":11,
    "Value":-15.6527777778,
    "Agent":"C2D"
  },
  {
    "Iteration":12,
    "Value":-16.2112676056,
    "Agent":"C2D"
  },
  {
    "Iteration":13,
    "Value":-16.5633802817,
    "Agent":"C2D"
  },
  {
    "Iteration":14,
    "Value":-15.3888888889,
    "Agent":"C2D"
  },
  {
    "Iteration":15,
    "Value":-15.9436619718,
    "Agent":"C2D"
  },
  {
    "Iteration":16,
    "Value":-14.1111111111,
    "Agent":"C2D"
  },
  {
    "Iteration":17,
    "Value":-15.4583333333,
    "Agent":"C2D"
  },
  {
    "Iteration":18,
    "Value":-15.4166666667,
    "Agent":"C2D"
  },
  {
    "Iteration":19,
    "Value":-16.3802816901,
    "Agent":"C2D"
  },
  {
    "Iteration":20,
    "Value":-16.6388888889,
    "Agent":"C2D"
  },
  {
    "Iteration":21,
    "Value":-15.5972222222,
    "Agent":"C2D"
  },
  {
    "Iteration":22,
    "Value":-16.0985915493,
    "Agent":"C2D"
  },
  {
    "Iteration":23,
    "Value":-14.8873239437,
    "Agent":"C2D"
  },
  {
    "Iteration":24,
    "Value":-15.5633802817,
    "Agent":"C2D"
  },
  {
    "Iteration":25,
    "Value":-15.5972222222,
    "Agent":"C2D"
  },
  {
    "Iteration":26,
    "Value":-15.6111111111,
    "Agent":"C2D"
  },
  {
    "Iteration":27,
    "Value":-15.8055555556,
    "Agent":"C2D"
  },
  {
    "Iteration":28,
    "Value":-13.9452054795,
    "Agent":"C2D"
  },
  {
    "Iteration":29,
    "Value":-12.5753424658,
    "Agent":"C2D"
  },
  {
    "Iteration":30,
    "Value":-11.6,
    "Agent":"C2D"
  },
  {
    "Iteration":31,
    "Value":-12.4864864865,
    "Agent":"C2D"
  },
  {
    "Iteration":32,
    "Value":-11.4133333333,
    "Agent":"C2D"
  },
  {
    "Iteration":33,
    "Value":-10.4545454545,
    "Agent":"C2D"
  },
  {
    "Iteration":34,
    "Value":-10.4078947368,
    "Agent":"C2D"
  },
  {
    "Iteration":35,
    "Value":-10.025974026,
    "Agent":"C2D"
  },
  {
    "Iteration":36,
    "Value":-10.2077922078,
    "Agent":"C2D"
  },
  {
    "Iteration":37,
    "Value":-9.3076923077,
    "Agent":"C2D"
  },
  {
    "Iteration":38,
    "Value":-9.4025974026,
    "Agent":"C2D"
  },
  {
    "Iteration":39,
    "Value":-9.1038961039,
    "Agent":"C2D"
  },
  {
    "Iteration":40,
    "Value":-9.7792207792,
    "Agent":"C2D"
  },
  {
    "Iteration":41,
    "Value":-10.0657894737,
    "Agent":"C2D"
  },
  {
    "Iteration":42,
    "Value":-9.4743589744,
    "Agent":"C2D"
  },
  {
    "Iteration":43,
    "Value":-10.0649350649,
    "Agent":"C2D"
  },
  {
    "Iteration":44,
    "Value":-9.8181818182,
    "Agent":"C2D"
  },
  {
    "Iteration":45,
    "Value":-8.5443037975,
    "Agent":"C2D"
  },
  {
    "Iteration":46,
    "Value":-8.2658227848,
    "Agent":"C2D"
  },
  {
    "Iteration":47,
    "Value":-8.0384615385,
    "Agent":"C2D"
  },
  {
    "Iteration":48,
    "Value":-7.4683544304,
    "Agent":"C2D"
  },
  {
    "Iteration":49,
    "Value":-8.3333333333,
    "Agent":"C2D"
  },
  {
    "Iteration":50,
    "Value":-8.5064935065,
    "Agent":"C2D"
  },
  {
    "Iteration":51,
    "Value":-8.4675324675,
    "Agent":"C2D"
  },
  {
    "Iteration":52,
    "Value":-7.4078947368,
    "Agent":"C2D"
  },
  {
    "Iteration":53,
    "Value":-7.2564102564,
    "Agent":"C2D"
  },
  {
    "Iteration":54,
    "Value":-6.7820512821,
    "Agent":"C2D"
  },
  {
    "Iteration":55,
    "Value":-6.987012987,
    "Agent":"C2D"
  },
  {
    "Iteration":56,
    "Value":-6.2987012987,
    "Agent":"C2D"
  },
  {
    "Iteration":57,
    "Value":-7.0128205128,
    "Agent":"C2D"
  },
  {
    "Iteration":58,
    "Value":-5.858974359,
    "Agent":"C2D"
  },
  {
    "Iteration":59,
    "Value":-5.8831168831,
    "Agent":"C2D"
  },
  {
    "Iteration":60,
    "Value":-5.358974359,
    "Agent":"C2D"
  },
  {
    "Iteration":61,
    "Value":-4.9090909091,
    "Agent":"C2D"
  },
  {
    "Iteration":62,
    "Value":-5.0128205128,
    "Agent":"C2D"
  },
  {
    "Iteration":63,
    "Value":-5.1315789474,
    "Agent":"C2D"
  },
  {
    "Iteration":64,
    "Value":-4.4615384615,
    "Agent":"C2D"
  },
  {
    "Iteration":65,
    "Value":-5.2051282051,
    "Agent":"C2D"
  },
  {
    "Iteration":66,
    "Value":-5.1948051948,
    "Agent":"C2D"
  },
  {
    "Iteration":67,
    "Value":-4.5714285714,
    "Agent":"C2D"
  },
  {
    "Iteration":68,
    "Value":-4.5384615385,
    "Agent":"C2D"
  },
  {
    "Iteration":69,
    "Value":-4.417721519,
    "Agent":"C2D"
  },
  {
    "Iteration":70,
    "Value":-4.4102564103,
    "Agent":"C2D"
  },
  {
    "Iteration":71,
    "Value":-3.9615384615,
    "Agent":"C2D"
  },
  {
    "Iteration":72,
    "Value":-4.2692307692,
    "Agent":"C2D"
  },
  {
    "Iteration":73,
    "Value":-3.835443038,
    "Agent":"C2D"
  },
  {
    "Iteration":74,
    "Value":-4.1666666667,
    "Agent":"C2D"
  },
  {
    "Iteration":75,
    "Value":-4.3544303797,
    "Agent":"C2D"
  },
  {
    "Iteration":76,
    "Value":-4.2564102564,
    "Agent":"C2D"
  },
  {
    "Iteration":77,
    "Value":-3.5844155844,
    "Agent":"C2D"
  },
  {
    "Iteration":78,
    "Value":-3.7792207792,
    "Agent":"C2D"
  },
  {
    "Iteration":79,
    "Value":-3.7564102564,
    "Agent":"C2D"
  },
  {
    "Iteration":80,
    "Value":-4.2435897436,
    "Agent":"C2D"
  },
  {
    "Iteration":81,
    "Value":-4.0649350649,
    "Agent":"C2D"
  },
  {
    "Iteration":82,
    "Value":-4.3076923077,
    "Agent":"C2D"
  },
  {
    "Iteration":83,
    "Value":-4.6363636364,
    "Agent":"C2D"
  },
  {
    "Iteration":84,
    "Value":-4.4556962025,
    "Agent":"C2D"
  },
  {
    "Iteration":85,
    "Value":-4.0128205128,
    "Agent":"C2D"
  },
  {
    "Iteration":86,
    "Value":-3.8051948052,
    "Agent":"C2D"
  },
  {
    "Iteration":87,
    "Value":-3.9102564103,
    "Agent":"C2D"
  },
  {
    "Iteration":88,
    "Value":-3.4430379747,
    "Agent":"C2D"
  },
  {
    "Iteration":89,
    "Value":-4.0,
    "Agent":"C2D"
  },
  {
    "Iteration":90,
    "Value":-3.8205128205,
    "Agent":"C2D"
  },
  {
    "Iteration":91,
    "Value":-3.9240506329,
    "Agent":"C2D"
  },
  {
    "Iteration":92,
    "Value":-4.0897435897,
    "Agent":"C2D"
  },
  {
    "Iteration":93,
    "Value":-4.5384615385,
    "Agent":"C2D"
  },
  {
    "Iteration":94,
    "Value":-3.8701298701,
    "Agent":"C2D"
  },
  {
    "Iteration":95,
    "Value":-4.417721519,
    "Agent":"C2D"
  },
  {
    "Iteration":96,
    "Value":-4.038961039,
    "Agent":"C2D"
  },
  {
    "Iteration":97,
    "Value":-4.7692307692,
    "Agent":"C2D"
  },
  {
    "Iteration":98,
    "Value":-5.2467532468,
    "Agent":"C2D"
  },
  {
    "Iteration":99,
    "Value":-4.3076923077,
    "Agent":"C2D"
  },
  {
    "Iteration":100,
    "Value":-3.8421052632,
    "Agent":"C2D"
  },
  {
    "Iteration":101,
    "Value":-4.3037974684,
    "Agent":"C2D"
  },
  {
    "Iteration":102,
    "Value":-4.2948717949,
    "Agent":"C2D"
  },
  {
    "Iteration":103,
    "Value":-4.5696202532,
    "Agent":"C2D"
  },
  {
    "Iteration":104,
    "Value":-4.5,
    "Agent":"C2D"
  },
  {
    "Iteration":105,
    "Value":-5.1025641026,
    "Agent":"C2D"
  },
  {
    "Iteration":106,
    "Value":-4.141025641,
    "Agent":"C2D"
  },
  {
    "Iteration":107,
    "Value":-3.9102564103,
    "Agent":"C2D"
  },
  {
    "Iteration":108,
    "Value":-4.038961039,
    "Agent":"C2D"
  },
  {
    "Iteration":109,
    "Value":-4.5,
    "Agent":"C2D"
  },
  {
    "Iteration":110,
    "Value":-4.4155844156,
    "Agent":"C2D"
  },
  {
    "Iteration":111,
    "Value":-4.5194805195,
    "Agent":"C2D"
  },
  {
    "Iteration":112,
    "Value":-3.5569620253,
    "Agent":"C2D"
  },
  {
    "Iteration":113,
    "Value":-3.8717948718,
    "Agent":"C2D"
  },
  {
    "Iteration":114,
    "Value":-3.8311688312,
    "Agent":"C2D"
  },
  {
    "Iteration":115,
    "Value":-4.2692307692,
    "Agent":"C2D"
  },
  {
    "Iteration":116,
    "Value":-4.4102564103,
    "Agent":"C2D"
  },
  {
    "Iteration":117,
    "Value":-4.2763157895,
    "Agent":"C2D"
  },
  {
    "Iteration":118,
    "Value":-4.7631578947,
    "Agent":"C2D"
  },
  {
    "Iteration":119,
    "Value":-4.5064935065,
    "Agent":"C2D"
  },
  {
    "Iteration":120,
    "Value":-4.2857142857,
    "Agent":"C2D"
  },
  {
    "Iteration":121,
    "Value":-4.3636363636,
    "Agent":"C2D"
  },
  {
    "Iteration":122,
    "Value":-4.6710526316,
    "Agent":"C2D"
  },
  {
    "Iteration":123,
    "Value":-4.4871794872,
    "Agent":"C2D"
  },
  {
    "Iteration":124,
    "Value":-4.7922077922,
    "Agent":"C2D"
  },
  {
    "Iteration":125,
    "Value":-4.4936708861,
    "Agent":"C2D"
  },
  {
    "Iteration":126,
    "Value":-3.7307692308,
    "Agent":"C2D"
  },
  {
    "Iteration":127,
    "Value":-4.1538461538,
    "Agent":"C2D"
  },
  {
    "Iteration":128,
    "Value":-4.6710526316,
    "Agent":"C2D"
  },
  {
    "Iteration":129,
    "Value":-4.4102564103,
    "Agent":"C2D"
  },
  {
    "Iteration":130,
    "Value":-4.3717948718,
    "Agent":"C2D"
  },
  {
    "Iteration":131,
    "Value":-5.0263157895,
    "Agent":"C2D"
  },
  {
    "Iteration":132,
    "Value":-4.8421052632,
    "Agent":"C2D"
  },
  {
    "Iteration":133,
    "Value":-4.8181818182,
    "Agent":"C2D"
  },
  {
    "Iteration":134,
    "Value":-4.8846153846,
    "Agent":"C2D"
  },
  {
    "Iteration":135,
    "Value":-4.3461538462,
    "Agent":"C2D"
  },
  {
    "Iteration":136,
    "Value":-4.1538461538,
    "Agent":"C2D"
  },
  {
    "Iteration":137,
    "Value":-4.641025641,
    "Agent":"C2D"
  },
  {
    "Iteration":138,
    "Value":-3.9473684211,
    "Agent":"C2D"
  },
  {
    "Iteration":139,
    "Value":-4.6233766234,
    "Agent":"C2D"
  },
  {
    "Iteration":140,
    "Value":-4.5921052632,
    "Agent":"C2D"
  },
  {
    "Iteration":141,
    "Value":-5.2727272727,
    "Agent":"C2D"
  },
  {
    "Iteration":142,
    "Value":-3.7922077922,
    "Agent":"C2D"
  },
  {
    "Iteration":143,
    "Value":-4.7532467532,
    "Agent":"C2D"
  },
  {
    "Iteration":144,
    "Value":-4.1948051948,
    "Agent":"C2D"
  },
  {
    "Iteration":145,
    "Value":-3.6883116883,
    "Agent":"C2D"
  },
  {
    "Iteration":146,
    "Value":-4.4605263158,
    "Agent":"C2D"
  },
  {
    "Iteration":147,
    "Value":-4.7179487179,
    "Agent":"C2D"
  },
  {
    "Iteration":148,
    "Value":-4.1153846154,
    "Agent":"C2D"
  },
  {
    "Iteration":149,
    "Value":-3.8961038961,
    "Agent":"C2D"
  },
  {
    "Iteration":150,
    "Value":-4.5324675325,
    "Agent":"C2D"
  },
  {
    "Iteration":151,
    "Value":-4.56,
    "Agent":"C2D"
  },
  {
    "Iteration":152,
    "Value":-4.2820512821,
    "Agent":"C2D"
  },
  {
    "Iteration":153,
    "Value":-4.3815789474,
    "Agent":"C2D"
  },
  {
    "Iteration":154,
    "Value":-4.974025974,
    "Agent":"C2D"
  },
  {
    "Iteration":155,
    "Value":-4.5131578947,
    "Agent":"C2D"
  },
  {
    "Iteration":156,
    "Value":-4.6883116883,
    "Agent":"C2D"
  },
  {
    "Iteration":157,
    "Value":-4.2077922078,
    "Agent":"C2D"
  },
  {
    "Iteration":158,
    "Value":-4.8552631579,
    "Agent":"C2D"
  },
  {
    "Iteration":159,
    "Value":-5.1038961039,
    "Agent":"C2D"
  },
  {
    "Iteration":160,
    "Value":-4.1973684211,
    "Agent":"C2D"
  },
  {
    "Iteration":161,
    "Value":-4.3376623377,
    "Agent":"C2D"
  },
  {
    "Iteration":162,
    "Value":-4.5064935065,
    "Agent":"C2D"
  },
  {
    "Iteration":163,
    "Value":-4.4342105263,
    "Agent":"C2D"
  },
  {
    "Iteration":164,
    "Value":-4.1025641026,
    "Agent":"C2D"
  },
  {
    "Iteration":165,
    "Value":-4.0,
    "Agent":"C2D"
  },
  {
    "Iteration":166,
    "Value":-4.5131578947,
    "Agent":"C2D"
  },
  {
    "Iteration":167,
    "Value":-4.2894736842,
    "Agent":"C2D"
  },
  {
    "Iteration":168,
    "Value":-4.5657894737,
    "Agent":"C2D"
  },
  {
    "Iteration":169,
    "Value":-4.5,
    "Agent":"C2D"
  },
  {
    "Iteration":170,
    "Value":-3.6184210526,
    "Agent":"C2D"
  },
  {
    "Iteration":171,
    "Value":-4.5789473684,
    "Agent":"C2D"
  },
  {
    "Iteration":172,
    "Value":-4.64,
    "Agent":"C2D"
  },
  {
    "Iteration":173,
    "Value":-4.7631578947,
    "Agent":"C2D"
  },
  {
    "Iteration":174,
    "Value":-5.3866666667,
    "Agent":"C2D"
  },
  {
    "Iteration":175,
    "Value":-4.3466666667,
    "Agent":"C2D"
  },
  {
    "Iteration":176,
    "Value":-5.3108108108,
    "Agent":"C2D"
  },
  {
    "Iteration":177,
    "Value":-4.1052631579,
    "Agent":"C2D"
  },
  {
    "Iteration":178,
    "Value":-4.6533333333,
    "Agent":"C2D"
  },
  {
    "Iteration":179,
    "Value":-5.3552631579,
    "Agent":"C2D"
  },
  {
    "Iteration":180,
    "Value":-4.8783783784,
    "Agent":"C2D"
  },
  {
    "Iteration":181,
    "Value":-5.28,
    "Agent":"C2D"
  },
  {
    "Iteration":182,
    "Value":-5.2027027027,
    "Agent":"C2D"
  },
  {
    "Iteration":183,
    "Value":-5.1315789474,
    "Agent":"C2D"
  },
  {
    "Iteration":184,
    "Value":-4.7763157895,
    "Agent":"C2D"
  },
  {
    "Iteration":185,
    "Value":-4.8933333333,
    "Agent":"C2D"
  },
  {
    "Iteration":186,
    "Value":-4.5466666667,
    "Agent":"C2D"
  },
  {
    "Iteration":187,
    "Value":-4.64,
    "Agent":"C2D"
  },
  {
    "Iteration":188,
    "Value":-4.8684210526,
    "Agent":"C2D"
  },
  {
    "Iteration":189,
    "Value":-4.8266666667,
    "Agent":"C2D"
  },
  {
    "Iteration":190,
    "Value":-3.9605263158,
    "Agent":"C2D"
  },
  {
    "Iteration":191,
    "Value":-4.44,
    "Agent":"C2D"
  },
  {
    "Iteration":192,
    "Value":-4.6891891892,
    "Agent":"C2D"
  },
  {
    "Iteration":193,
    "Value":-4.64,
    "Agent":"C2D"
  },
  {
    "Iteration":194,
    "Value":-4.4210526316,
    "Agent":"C2D"
  },
  {
    "Iteration":195,
    "Value":-4.1578947368,
    "Agent":"C2D"
  },
  {
    "Iteration":196,
    "Value":-4.4933333333,
    "Agent":"C2D"
  },
  {
    "Iteration":197,
    "Value":-4.9864864865,
    "Agent":"C2D"
  },
  {
    "Iteration":198,
    "Value":-4.5866666667,
    "Agent":"C2D"
  },
  {
    "Iteration":199,
    "Value":-4.7702702703,
    "Agent":"C2D"
  },
  {
    "Iteration":0,
    "Value":-12.1351351351,
    "Agent":"C2D"
  },
  {
    "Iteration":1,
    "Value":-15.5694444444,
    "Agent":"C2D"
  },
  {
    "Iteration":2,
    "Value":-14.6944444444,
    "Agent":"C2D"
  },
  {
    "Iteration":3,
    "Value":-15.4931506849,
    "Agent":"C2D"
  },
  {
    "Iteration":4,
    "Value":-14.875,
    "Agent":"C2D"
  },
  {
    "Iteration":5,
    "Value":-15.625,
    "Agent":"C2D"
  },
  {
    "Iteration":6,
    "Value":-14.0547945205,
    "Agent":"C2D"
  },
  {
    "Iteration":7,
    "Value":-15.7638888889,
    "Agent":"C2D"
  },
  {
    "Iteration":8,
    "Value":-15.1805555556,
    "Agent":"C2D"
  },
  {
    "Iteration":9,
    "Value":-15.9295774648,
    "Agent":"C2D"
  },
  {
    "Iteration":10,
    "Value":-15.8472222222,
    "Agent":"C2D"
  },
  {
    "Iteration":11,
    "Value":-16.3661971831,
    "Agent":"C2D"
  },
  {
    "Iteration":12,
    "Value":-15.8333333333,
    "Agent":"C2D"
  },
  {
    "Iteration":13,
    "Value":-16.0277777778,
    "Agent":"C2D"
  },
  {
    "Iteration":14,
    "Value":-16.5277777778,
    "Agent":"C2D"
  },
  {
    "Iteration":15,
    "Value":-16.4507042254,
    "Agent":"C2D"
  },
  {
    "Iteration":16,
    "Value":-15.676056338,
    "Agent":"C2D"
  },
  {
    "Iteration":17,
    "Value":-15.1666666667,
    "Agent":"C2D"
  },
  {
    "Iteration":18,
    "Value":-14.985915493,
    "Agent":"C2D"
  },
  {
    "Iteration":19,
    "Value":-16.2394366197,
    "Agent":"C2D"
  },
  {
    "Iteration":20,
    "Value":-15.2083333333,
    "Agent":"C2D"
  },
  {
    "Iteration":21,
    "Value":-16.7887323944,
    "Agent":"C2D"
  },
  {
    "Iteration":22,
    "Value":-16.1666666667,
    "Agent":"C2D"
  },
  {
    "Iteration":23,
    "Value":-16.3521126761,
    "Agent":"C2D"
  },
  {
    "Iteration":24,
    "Value":-16.5694444444,
    "Agent":"C2D"
  },
  {
    "Iteration":25,
    "Value":-15.8309859155,
    "Agent":"C2D"
  },
  {
    "Iteration":26,
    "Value":-15.0273972603,
    "Agent":"C2D"
  },
  {
    "Iteration":27,
    "Value":-15.5555555556,
    "Agent":"C2D"
  },
  {
    "Iteration":28,
    "Value":-14.9452054795,
    "Agent":"C2D"
  },
  {
    "Iteration":29,
    "Value":-13.9863013699,
    "Agent":"C2D"
  },
  {
    "Iteration":30,
    "Value":-12.2533333333,
    "Agent":"C2D"
  },
  {
    "Iteration":31,
    "Value":-10.7466666667,
    "Agent":"C2D"
  },
  {
    "Iteration":32,
    "Value":-11.6533333333,
    "Agent":"C2D"
  },
  {
    "Iteration":33,
    "Value":-11.5733333333,
    "Agent":"C2D"
  },
  {
    "Iteration":34,
    "Value":-12.3333333333,
    "Agent":"C2D"
  },
  {
    "Iteration":35,
    "Value":-11.0657894737,
    "Agent":"C2D"
  },
  {
    "Iteration":36,
    "Value":-11.3466666667,
    "Agent":"C2D"
  },
  {
    "Iteration":37,
    "Value":-11.5466666667,
    "Agent":"C2D"
  },
  {
    "Iteration":38,
    "Value":-10.2564102564,
    "Agent":"C2D"
  },
  {
    "Iteration":39,
    "Value":-9.9342105263,
    "Agent":"C2D"
  },
  {
    "Iteration":40,
    "Value":-11.4736842105,
    "Agent":"C2D"
  },
  {
    "Iteration":41,
    "Value":-13.5540540541,
    "Agent":"C2D"
  },
  {
    "Iteration":42,
    "Value":-12.2533333333,
    "Agent":"C2D"
  },
  {
    "Iteration":43,
    "Value":-9.8157894737,
    "Agent":"C2D"
  },
  {
    "Iteration":44,
    "Value":-10.2666666667,
    "Agent":"C2D"
  },
  {
    "Iteration":45,
    "Value":-10.2077922078,
    "Agent":"C2D"
  },
  {
    "Iteration":46,
    "Value":-9.75,
    "Agent":"C2D"
  },
  {
    "Iteration":47,
    "Value":-9.7066666667,
    "Agent":"C2D"
  },
  {
    "Iteration":48,
    "Value":-9.6052631579,
    "Agent":"C2D"
  },
  {
    "Iteration":49,
    "Value":-8.7066666667,
    "Agent":"C2D"
  },
  {
    "Iteration":50,
    "Value":-9.36,
    "Agent":"C2D"
  },
  {
    "Iteration":51,
    "Value":-9.4,
    "Agent":"C2D"
  },
  {
    "Iteration":52,
    "Value":-8.8243243243,
    "Agent":"C2D"
  },
  {
    "Iteration":53,
    "Value":-9.8533333333,
    "Agent":"C2D"
  },
  {
    "Iteration":54,
    "Value":-8.6315789474,
    "Agent":"C2D"
  },
  {
    "Iteration":55,
    "Value":-8.3157894737,
    "Agent":"C2D"
  },
  {
    "Iteration":56,
    "Value":-8.4933333333,
    "Agent":"C2D"
  },
  {
    "Iteration":57,
    "Value":-8.0789473684,
    "Agent":"C2D"
  },
  {
    "Iteration":58,
    "Value":-7.4078947368,
    "Agent":"C2D"
  },
  {
    "Iteration":59,
    "Value":-7.0263157895,
    "Agent":"C2D"
  },
  {
    "Iteration":60,
    "Value":-6.8,
    "Agent":"C2D"
  },
  {
    "Iteration":61,
    "Value":-8.5921052632,
    "Agent":"C2D"
  },
  {
    "Iteration":62,
    "Value":-8.1558441558,
    "Agent":"C2D"
  },
  {
    "Iteration":63,
    "Value":-7.1298701299,
    "Agent":"C2D"
  },
  {
    "Iteration":64,
    "Value":-7.8181818182,
    "Agent":"C2D"
  },
  {
    "Iteration":65,
    "Value":-6.9342105263,
    "Agent":"C2D"
  },
  {
    "Iteration":66,
    "Value":-7.5921052632,
    "Agent":"C2D"
  },
  {
    "Iteration":67,
    "Value":-6.6103896104,
    "Agent":"C2D"
  },
  {
    "Iteration":68,
    "Value":-7.1558441558,
    "Agent":"C2D"
  },
  {
    "Iteration":69,
    "Value":-6.2337662338,
    "Agent":"C2D"
  },
  {
    "Iteration":70,
    "Value":-6.9342105263,
    "Agent":"C2D"
  },
  {
    "Iteration":71,
    "Value":-6.5194805195,
    "Agent":"C2D"
  },
  {
    "Iteration":72,
    "Value":-6.1923076923,
    "Agent":"C2D"
  },
  {
    "Iteration":73,
    "Value":-5.7215189873,
    "Agent":"C2D"
  },
  {
    "Iteration":74,
    "Value":-6.0506329114,
    "Agent":"C2D"
  },
  {
    "Iteration":75,
    "Value":-6.2307692308,
    "Agent":"C2D"
  },
  {
    "Iteration":76,
    "Value":-5.4683544304,
    "Agent":"C2D"
  },
  {
    "Iteration":77,
    "Value":-5.9487179487,
    "Agent":"C2D"
  },
  {
    "Iteration":78,
    "Value":-5.7848101266,
    "Agent":"C2D"
  },
  {
    "Iteration":79,
    "Value":-5.7215189873,
    "Agent":"C2D"
  },
  {
    "Iteration":80,
    "Value":-5.3924050633,
    "Agent":"C2D"
  },
  {
    "Iteration":81,
    "Value":-4.9493670886,
    "Agent":"C2D"
  },
  {
    "Iteration":82,
    "Value":-4.8375,
    "Agent":"C2D"
  },
  {
    "Iteration":83,
    "Value":-4.8974358974,
    "Agent":"C2D"
  },
  {
    "Iteration":84,
    "Value":-5.2784810127,
    "Agent":"C2D"
  },
  {
    "Iteration":85,
    "Value":-5.175,
    "Agent":"C2D"
  },
  {
    "Iteration":86,
    "Value":-5.1012658228,
    "Agent":"C2D"
  },
  {
    "Iteration":87,
    "Value":-5.2025316456,
    "Agent":"C2D"
  },
  {
    "Iteration":88,
    "Value":-5.0125,
    "Agent":"C2D"
  },
  {
    "Iteration":89,
    "Value":-4.9746835443,
    "Agent":"C2D"
  },
  {
    "Iteration":90,
    "Value":-5.4358974359,
    "Agent":"C2D"
  },
  {
    "Iteration":91,
    "Value":-5.8974358974,
    "Agent":"C2D"
  },
  {
    "Iteration":92,
    "Value":-6.1282051282,
    "Agent":"C2D"
  },
  {
    "Iteration":93,
    "Value":-5.6666666667,
    "Agent":"C2D"
  },
  {
    "Iteration":94,
    "Value":-5.5897435897,
    "Agent":"C2D"
  },
  {
    "Iteration":95,
    "Value":-6.4025974026,
    "Agent":"C2D"
  },
  {
    "Iteration":96,
    "Value":-5.8441558442,
    "Agent":"C2D"
  },
  {
    "Iteration":97,
    "Value":-6.6025641026,
    "Agent":"C2D"
  },
  {
    "Iteration":98,
    "Value":-6.5657894737,
    "Agent":"C2D"
  },
  {
    "Iteration":99,
    "Value":-6.6973684211,
    "Agent":"C2D"
  },
  {
    "Iteration":100,
    "Value":-5.8961038961,
    "Agent":"C2D"
  },
  {
    "Iteration":101,
    "Value":-6.3733333333,
    "Agent":"C2D"
  },
  {
    "Iteration":102,
    "Value":-6.4605263158,
    "Agent":"C2D"
  },
  {
    "Iteration":103,
    "Value":-6.2266666667,
    "Agent":"C2D"
  },
  {
    "Iteration":104,
    "Value":-7.08,
    "Agent":"C2D"
  },
  {
    "Iteration":105,
    "Value":-6.4533333333,
    "Agent":"C2D"
  },
  {
    "Iteration":106,
    "Value":-6.5066666667,
    "Agent":"C2D"
  },
  {
    "Iteration":107,
    "Value":-7.12,
    "Agent":"C2D"
  },
  {
    "Iteration":108,
    "Value":-7.0,
    "Agent":"C2D"
  },
  {
    "Iteration":109,
    "Value":-7.6849315068,
    "Agent":"C2D"
  },
  {
    "Iteration":110,
    "Value":-5.7702702703,
    "Agent":"C2D"
  },
  {
    "Iteration":111,
    "Value":-5.8648648649,
    "Agent":"C2D"
  },
  {
    "Iteration":112,
    "Value":-5.3108108108,
    "Agent":"C2D"
  },
  {
    "Iteration":113,
    "Value":-5.08,
    "Agent":"C2D"
  },
  {
    "Iteration":114,
    "Value":-6.8108108108,
    "Agent":"C2D"
  },
  {
    "Iteration":115,
    "Value":-6.2162162162,
    "Agent":"C2D"
  },
  {
    "Iteration":116,
    "Value":-5.1558441558,
    "Agent":"C2D"
  },
  {
    "Iteration":117,
    "Value":-5.8933333333,
    "Agent":"C2D"
  },
  {
    "Iteration":118,
    "Value":-4.9733333333,
    "Agent":"C2D"
  },
  {
    "Iteration":119,
    "Value":-5.2533333333,
    "Agent":"C2D"
  },
  {
    "Iteration":120,
    "Value":-5.7236842105,
    "Agent":"C2D"
  },
  {
    "Iteration":121,
    "Value":-6.0,
    "Agent":"C2D"
  },
  {
    "Iteration":122,
    "Value":-5.8904109589,
    "Agent":"C2D"
  },
  {
    "Iteration":123,
    "Value":-5.1643835616,
    "Agent":"C2D"
  },
  {
    "Iteration":124,
    "Value":-5.4459459459,
    "Agent":"C2D"
  },
  {
    "Iteration":125,
    "Value":-5.7083333333,
    "Agent":"C2D"
  },
  {
    "Iteration":126,
    "Value":-6.4246575342,
    "Agent":"C2D"
  },
  {
    "Iteration":127,
    "Value":-4.7763157895,
    "Agent":"C2D"
  },
  {
    "Iteration":128,
    "Value":-5.3766233766,
    "Agent":"C2D"
  },
  {
    "Iteration":129,
    "Value":-5.32,
    "Agent":"C2D"
  },
  {
    "Iteration":130,
    "Value":-5.7432432432,
    "Agent":"C2D"
  },
  {
    "Iteration":131,
    "Value":-5.4189189189,
    "Agent":"C2D"
  },
  {
    "Iteration":132,
    "Value":-4.9868421053,
    "Agent":"C2D"
  },
  {
    "Iteration":133,
    "Value":-4.5466666667,
    "Agent":"C2D"
  },
  {
    "Iteration":134,
    "Value":-5.1621621622,
    "Agent":"C2D"
  },
  {
    "Iteration":135,
    "Value":-5.5405405405,
    "Agent":"C2D"
  },
  {
    "Iteration":136,
    "Value":-4.9066666667,
    "Agent":"C2D"
  },
  {
    "Iteration":137,
    "Value":-6.0945945946,
    "Agent":"C2D"
  },
  {
    "Iteration":138,
    "Value":-4.5810810811,
    "Agent":"C2D"
  },
  {
    "Iteration":139,
    "Value":-4.9078947368,
    "Agent":"C2D"
  },
  {
    "Iteration":140,
    "Value":-5.1710526316,
    "Agent":"C2D"
  },
  {
    "Iteration":141,
    "Value":-5.3513513514,
    "Agent":"C2D"
  },
  {
    "Iteration":142,
    "Value":-5.1184210526,
    "Agent":"C2D"
  },
  {
    "Iteration":143,
    "Value":-5.8082191781,
    "Agent":"C2D"
  },
  {
    "Iteration":144,
    "Value":-5.3157894737,
    "Agent":"C2D"
  },
  {
    "Iteration":145,
    "Value":-5.5540540541,
    "Agent":"C2D"
  },
  {
    "Iteration":146,
    "Value":-4.3108108108,
    "Agent":"C2D"
  },
  {
    "Iteration":147,
    "Value":-4.8133333333,
    "Agent":"C2D"
  },
  {
    "Iteration":148,
    "Value":-5.1095890411,
    "Agent":"C2D"
  },
  {
    "Iteration":149,
    "Value":-4.5,
    "Agent":"C2D"
  },
  {
    "Iteration":150,
    "Value":-5.1506849315,
    "Agent":"C2D"
  },
  {
    "Iteration":151,
    "Value":-4.72,
    "Agent":"C2D"
  },
  {
    "Iteration":152,
    "Value":-5.1866666667,
    "Agent":"C2D"
  },
  {
    "Iteration":153,
    "Value":-5.1891891892,
    "Agent":"C2D"
  },
  {
    "Iteration":154,
    "Value":-4.3733333333,
    "Agent":"C2D"
  },
  {
    "Iteration":155,
    "Value":-4.4133333333,
    "Agent":"C2D"
  },
  {
    "Iteration":156,
    "Value":-5.0533333333,
    "Agent":"C2D"
  },
  {
    "Iteration":157,
    "Value":-5.1081081081,
    "Agent":"C2D"
  },
  {
    "Iteration":158,
    "Value":-5.2933333333,
    "Agent":"C2D"
  },
  {
    "Iteration":159,
    "Value":-4.9178082192,
    "Agent":"C2D"
  },
  {
    "Iteration":160,
    "Value":-5.1081081081,
    "Agent":"C2D"
  },
  {
    "Iteration":161,
    "Value":-5.9452054795,
    "Agent":"C2D"
  },
  {
    "Iteration":162,
    "Value":-5.2602739726,
    "Agent":"C2D"
  },
  {
    "Iteration":163,
    "Value":-5.5,
    "Agent":"C2D"
  },
  {
    "Iteration":164,
    "Value":-5.16,
    "Agent":"C2D"
  },
  {
    "Iteration":165,
    "Value":-4.9466666667,
    "Agent":"C2D"
  },
  {
    "Iteration":166,
    "Value":-4.5333333333,
    "Agent":"C2D"
  },
  {
    "Iteration":167,
    "Value":-4.5733333333,
    "Agent":"C2D"
  },
  {
    "Iteration":168,
    "Value":-4.9466666667,
    "Agent":"C2D"
  },
  {
    "Iteration":169,
    "Value":-4.1066666667,
    "Agent":"C2D"
  },
  {
    "Iteration":170,
    "Value":-4.0533333333,
    "Agent":"C2D"
  },
  {
    "Iteration":171,
    "Value":-4.7733333333,
    "Agent":"C2D"
  },
  {
    "Iteration":172,
    "Value":-5.1351351351,
    "Agent":"C2D"
  },
  {
    "Iteration":173,
    "Value":-4.4520547945,
    "Agent":"C2D"
  },
  {
    "Iteration":174,
    "Value":-5.8513513514,
    "Agent":"C2D"
  },
  {
    "Iteration":175,
    "Value":-5.1486486486,
    "Agent":"C2D"
  },
  {
    "Iteration":176,
    "Value":-4.8266666667,
    "Agent":"C2D"
  },
  {
    "Iteration":177,
    "Value":-4.8648648649,
    "Agent":"C2D"
  },
  {
    "Iteration":178,
    "Value":-4.44,
    "Agent":"C2D"
  },
  {
    "Iteration":179,
    "Value":-4.48,
    "Agent":"C2D"
  },
  {
    "Iteration":180,
    "Value":-4.8266666667,
    "Agent":"C2D"
  },
  {
    "Iteration":181,
    "Value":-5.2027027027,
    "Agent":"C2D"
  },
  {
    "Iteration":182,
    "Value":-5.3918918919,
    "Agent":"C2D"
  },
  {
    "Iteration":183,
    "Value":-5.4246575342,
    "Agent":"C2D"
  },
  {
    "Iteration":184,
    "Value":-4.84,
    "Agent":"C2D"
  },
  {
    "Iteration":185,
    "Value":-5.8513513514,
    "Agent":"C2D"
  },
  {
    "Iteration":186,
    "Value":-4.9452054795,
    "Agent":"C2D"
  },
  {
    "Iteration":187,
    "Value":-5.0,
    "Agent":"C2D"
  },
  {
    "Iteration":188,
    "Value":-4.904109589,
    "Agent":"C2D"
  },
  {
    "Iteration":189,
    "Value":-4.9315068493,
    "Agent":"C2D"
  },
  {
    "Iteration":190,
    "Value":-5.1095890411,
    "Agent":"C2D"
  },
  {
    "Iteration":191,
    "Value":-4.9722222222,
    "Agent":"C2D"
  },
  {
    "Iteration":192,
    "Value":-4.5890410959,
    "Agent":"C2D"
  },
  {
    "Iteration":193,
    "Value":-5.602739726,
    "Agent":"C2D"
  },
  {
    "Iteration":194,
    "Value":-4.1756756757,
    "Agent":"C2D"
  },
  {
    "Iteration":195,
    "Value":-5.1351351351,
    "Agent":"C2D"
  },
  {
    "Iteration":196,
    "Value":-4.2432432432,
    "Agent":"C2D"
  },
  {
    "Iteration":197,
    "Value":-5.28,
    "Agent":"C2D"
  },
  {
    "Iteration":198,
    "Value":-5.0547945205,
    "Agent":"C2D"
  },
  {
    "Iteration":199,
    "Value":-4.8918918919,
    "Agent":"C2D"
  }
]