[
  {
    "Iteration":0,
    "Value":2043.7768240343,
    "Agent":"C2D"
  },
  {
    "Iteration":1,
    "Value":9805.7692307692,
    "Agent":"C2D"
  },
  {
    "Iteration":2,
    "Value":12256.8345323741,
    "Agent":"C2D"
  },
  {
    "Iteration":3,
    "Value":13969.0476190476,
    "Agent":"C2D"
  },
  {
    "Iteration":4,
    "Value":18967.2897196262,
    "Agent":"C2D"
  },
  {
    "Iteration":5,
    "Value":20825.8928571429,
    "Agent":"C2D"
  },
  {
    "Iteration":6,
    "Value":23344.3396226415,
    "Agent":"C2D"
  },
  {
    "Iteration":7,
    "Value":23841.3461538462,
    "Agent":"C2D"
  },
  {
    "Iteration":8,
    "Value":24909.0,
    "Agent":"C2D"
  },
  {
    "Iteration":9,
    "Value":25383.6734693878,
    "Agent":"C2D"
  },
  {
    "Iteration":10,
    "Value":24239.4230769231,
    "Agent":"C2D"
  },
  {
    "Iteration":11,
    "Value":24607.9207920792,
    "Agent":"C2D"
  },
  {
    "Iteration":12,
    "Value":23223.6363636364,
    "Agent":"C2D"
  },
  {
    "Iteration":13,
    "Value":24497.1428571429,
    "Agent":"C2D"
  },
  {
    "Iteration":14,
    "Value":27261.8556701031,
    "Agent":"C2D"
  },
  {
    "Iteration":15,
    "Value":24631.7307692308,
    "Agent":"C2D"
  },
  {
    "Iteration":16,
    "Value":25214.5631067961,
    "Agent":"C2D"
  },
  {
    "Iteration":17,
    "Value":26312.1212121212,
    "Agent":"C2D"
  },
  {
    "Iteration":18,
    "Value":27425.2525252525,
    "Agent":"C2D"
  },
  {
    "Iteration":19,
    "Value":26450.9803921569,
    "Agent":"C2D"
  },
  {
    "Iteration":20,
    "Value":24908.5714285714,
    "Agent":"C2D"
  },
  {
    "Iteration":21,
    "Value":28442.1052631579,
    "Agent":"C2D"
  },
  {
    "Iteration":22,
    "Value":26595.0495049505,
    "Agent":"C2D"
  },
  {
    "Iteration":23,
    "Value":27003.0,
    "Agent":"C2D"
  },
  {
    "Iteration":24,
    "Value":27051.5463917526,
    "Agent":"C2D"
  },
  {
    "Iteration":25,
    "Value":26997.0,
    "Agent":"C2D"
  },
  {
    "Iteration":26,
    "Value":25866.3461538462,
    "Agent":"C2D"
  },
  {
    "Iteration":27,
    "Value":26962.0,
    "Agent":"C2D"
  },
  {
    "Iteration":28,
    "Value":27807.1428571429,
    "Agent":"C2D"
  },
  {
    "Iteration":29,
    "Value":26467.3267326733,
    "Agent":"C2D"
  },
  {
    "Iteration":30,
    "Value":27660.6060606061,
    "Agent":"C2D"
  },
  {
    "Iteration":31,
    "Value":27800.0,
    "Agent":"C2D"
  },
  {
    "Iteration":32,
    "Value":28686.170212766,
    "Agent":"C2D"
  },
  {
    "Iteration":33,
    "Value":27830.9278350515,
    "Agent":"C2D"
  },
  {
    "Iteration":34,
    "Value":29169.1489361702,
    "Agent":"C2D"
  },
  {
    "Iteration":35,
    "Value":28170.8333333333,
    "Agent":"C2D"
  },
  {
    "Iteration":36,
    "Value":27308.1632653061,
    "Agent":"C2D"
  },
  {
    "Iteration":37,
    "Value":29087.2340425532,
    "Agent":"C2D"
  },
  {
    "Iteration":38,
    "Value":28955.3191489362,
    "Agent":"C2D"
  },
  {
    "Iteration":39,
    "Value":28601.0526315789,
    "Agent":"C2D"
  },
  {
    "Iteration":40,
    "Value":28822.1052631579,
    "Agent":"C2D"
  },
  {
    "Iteration":41,
    "Value":28309.375,
    "Agent":"C2D"
  },
  {
    "Iteration":42,
    "Value":27789.6907216495,
    "Agent":"C2D"
  },
  {
    "Iteration":43,
    "Value":29952.1739130435,
    "Agent":"C2D"
  },
  {
    "Iteration":44,
    "Value":30881.3186813187,
    "Agent":"C2D"
  },
  {
    "Iteration":45,
    "Value":29819.3548387097,
    "Agent":"C2D"
  },
  {
    "Iteration":46,
    "Value":29310.752688172,
    "Agent":"C2D"
  },
  {
    "Iteration":47,
    "Value":30239.5604395604,
    "Agent":"C2D"
  },
  {
    "Iteration":48,
    "Value":32340.6976744186,
    "Agent":"C2D"
  },
  {
    "Iteration":49,
    "Value":31504.4444444444,
    "Agent":"C2D"
  },
  {
    "Iteration":50,
    "Value":31884.2696629213,
    "Agent":"C2D"
  },
  {
    "Iteration":51,
    "Value":30180.2197802198,
    "Agent":"C2D"
  },
  {
    "Iteration":52,
    "Value":28193.75,
    "Agent":"C2D"
  },
  {
    "Iteration":53,
    "Value":28785.4166666667,
    "Agent":"C2D"
  },
  {
    "Iteration":54,
    "Value":32105.7471264368,
    "Agent":"C2D"
  },
  {
    "Iteration":55,
    "Value":30196.7391304348,
    "Agent":"C2D"
  },
  {
    "Iteration":56,
    "Value":30214.1304347826,
    "Agent":"C2D"
  },
  {
    "Iteration":57,
    "Value":33720.2380952381,
    "Agent":"C2D"
  },
  {
    "Iteration":58,
    "Value":32515.1162790698,
    "Agent":"C2D"
  },
  {
    "Iteration":59,
    "Value":32708.0459770115,
    "Agent":"C2D"
  },
  {
    "Iteration":60,
    "Value":31190.0,
    "Agent":"C2D"
  },
  {
    "Iteration":61,
    "Value":31707.9545454545,
    "Agent":"C2D"
  },
  {
    "Iteration":62,
    "Value":30363.7362637363,
    "Agent":"C2D"
  },
  {
    "Iteration":63,
    "Value":29124.4680851064,
    "Agent":"C2D"
  },
  {
    "Iteration":64,
    "Value":30249.4505494506,
    "Agent":"C2D"
  },
  {
    "Iteration":65,
    "Value":33045.9770114943,
    "Agent":"C2D"
  },
  {
    "Iteration":66,
    "Value":30570.3296703297,
    "Agent":"C2D"
  },
  {
    "Iteration":67,
    "Value":32798.8505747126,
    "Agent":"C2D"
  },
  {
    "Iteration":68,
    "Value":32960.4651162791,
    "Agent":"C2D"
  },
  {
    "Iteration":69,
    "Value":33052.9411764706,
    "Agent":"C2D"
  },
  {
    "Iteration":70,
    "Value":32273.5632183908,
    "Agent":"C2D"
  },
  {
    "Iteration":71,
    "Value":28738.2978723404,
    "Agent":"C2D"
  },
  {
    "Iteration":72,
    "Value":30602.2222222222,
    "Agent":"C2D"
  },
  {
    "Iteration":73,
    "Value":31024.1758241758,
    "Agent":"C2D"
  },
  {
    "Iteration":74,
    "Value":31122.7272727273,
    "Agent":"C2D"
  },
  {
    "Iteration":75,
    "Value":31026.9662921348,
    "Agent":"C2D"
  },
  {
    "Iteration":76,
    "Value":33088.0952380952,
    "Agent":"C2D"
  },
  {
    "Iteration":77,
    "Value":32840.6976744186,
    "Agent":"C2D"
  },
  {
    "Iteration":78,
    "Value":34546.3414634146,
    "Agent":"C2D"
  },
  {
    "Iteration":79,
    "Value":34650.0,
    "Agent":"C2D"
  },
  {
    "Iteration":80,
    "Value":30150.5494505494,
    "Agent":"C2D"
  },
  {
    "Iteration":81,
    "Value":29007.4468085106,
    "Agent":"C2D"
  },
  {
    "Iteration":82,
    "Value":31276.404494382,
    "Agent":"C2D"
  },
  {
    "Iteration":83,
    "Value":31447.1264367816,
    "Agent":"C2D"
  },
  {
    "Iteration":84,
    "Value":31828.7356321839,
    "Agent":"C2D"
  },
  {
    "Iteration":85,
    "Value":31844.9438202247,
    "Agent":"C2D"
  },
  {
    "Iteration":86,
    "Value":33032.5581395349,
    "Agent":"C2D"
  },
  {
    "Iteration":87,
    "Value":30535.1648351648,
    "Agent":"C2D"
  },
  {
    "Iteration":88,
    "Value":32431.8181818182,
    "Agent":"C2D"
  },
  {
    "Iteration":89,
    "Value":32266.2790697674,
    "Agent":"C2D"
  },
  {
    "Iteration":90,
    "Value":32985.0574712644,
    "Agent":"C2D"
  },
  {
    "Iteration":91,
    "Value":32116.8539325843,
    "Agent":"C2D"
  },
  {
    "Iteration":92,
    "Value":32872.4137931034,
    "Agent":"C2D"
  },
  {
    "Iteration":93,
    "Value":34426.8292682927,
    "Agent":"C2D"
  },
  {
    "Iteration":94,
    "Value":35277.7777777778,
    "Agent":"C2D"
  },
  {
    "Iteration":95,
    "Value":34135.3658536585,
    "Agent":"C2D"
  },
  {
    "Iteration":96,
    "Value":33867.8571428571,
    "Agent":"C2D"
  },
  {
    "Iteration":97,
    "Value":33325.0,
    "Agent":"C2D"
  },
  {
    "Iteration":98,
    "Value":33840.4761904762,
    "Agent":"C2D"
  },
  {
    "Iteration":99,
    "Value":32544.1860465116,
    "Agent":"C2D"
  },
  {
    "Iteration":100,
    "Value":30886.8131868132,
    "Agent":"C2D"
  },
  {
    "Iteration":101,
    "Value":31462.5,
    "Agent":"C2D"
  },
  {
    "Iteration":102,
    "Value":35755.5555555556,
    "Agent":"C2D"
  },
  {
    "Iteration":103,
    "Value":34020.7317073171,
    "Agent":"C2D"
  },
  {
    "Iteration":104,
    "Value":33402.3529411765,
    "Agent":"C2D"
  },
  {
    "Iteration":105,
    "Value":34709.756097561,
    "Agent":"C2D"
  },
  {
    "Iteration":106,
    "Value":34626.8292682927,
    "Agent":"C2D"
  },
  {
    "Iteration":107,
    "Value":34882.9268292683,
    "Agent":"C2D"
  },
  {
    "Iteration":108,
    "Value":37477.9220779221,
    "Agent":"C2D"
  },
  {
    "Iteration":109,
    "Value":37066.2337662338,
    "Agent":"C2D"
  },
  {
    "Iteration":110,
    "Value":38367.1052631579,
    "Agent":"C2D"
  },
  {
    "Iteration":111,
    "Value":36452.5641025641,
    "Agent":"C2D"
  },
  {
    "Iteration":112,
    "Value":35158.5365853659,
    "Agent":"C2D"
  },
  {
    "Iteration":113,
    "Value":36284.6153846154,
    "Agent":"C2D"
  },
  {
    "Iteration":114,
    "Value":33513.9534883721,
    "Agent":"C2D"
  },
  {
    "Iteration":115,
    "Value":33751.2195121951,
    "Agent":"C2D"
  },
  {
    "Iteration":116,
    "Value":31532.9545454545,
    "Agent":"C2D"
  },
  {
    "Iteration":117,
    "Value":29929.347826087,
    "Agent":"C2D"
  },
  {
    "Iteration":118,
    "Value":33394.1176470588,
    "Agent":"C2D"
  },
  {
    "Iteration":119,
    "Value":31917.9775280899,
    "Agent":"C2D"
  },
  {
    "Iteration":120,
    "Value":32732.183908046,
    "Agent":"C2D"
  },
  {
    "Iteration":121,
    "Value":32408.1395348837,
    "Agent":"C2D"
  },
  {
    "Iteration":122,
    "Value":33465.4761904762,
    "Agent":"C2D"
  },
  {
    "Iteration":123,
    "Value":32305.8139534884,
    "Agent":"C2D"
  },
  {
    "Iteration":124,
    "Value":36665.3846153846,
    "Agent":"C2D"
  },
  {
    "Iteration":125,
    "Value":36170.0,
    "Agent":"C2D"
  },
  {
    "Iteration":126,
    "Value":36500.0,
    "Agent":"C2D"
  },
  {
    "Iteration":127,
    "Value":35702.4691358025,
    "Agent":"C2D"
  },
  {
    "Iteration":128,
    "Value":37342.3076923077,
    "Agent":"C2D"
  },
  {
    "Iteration":129,
    "Value":36882.0512820513,
    "Agent":"C2D"
  },
  {
    "Iteration":130,
    "Value":37340.2597402597,
    "Agent":"C2D"
  },
  {
    "Iteration":131,
    "Value":38931.0810810811,
    "Agent":"C2D"
  },
  {
    "Iteration":132,
    "Value":39390.4109589041,
    "Agent":"C2D"
  },
  {
    "Iteration":133,
    "Value":34167.9012345679,
    "Agent":"C2D"
  },
  {
    "Iteration":134,
    "Value":35989.8734177215,
    "Agent":"C2D"
  },
  {
    "Iteration":135,
    "Value":35860.7594936709,
    "Agent":"C2D"
  },
  {
    "Iteration":136,
    "Value":36416.4556962025,
    "Agent":"C2D"
  },
  {
    "Iteration":137,
    "Value":38193.3333333333,
    "Agent":"C2D"
  },
  {
    "Iteration":138,
    "Value":36558.9743589744,
    "Agent":"C2D"
  },
  {
    "Iteration":139,
    "Value":37277.9220779221,
    "Agent":"C2D"
  },
  {
    "Iteration":140,
    "Value":36113.75,
    "Agent":"C2D"
  },
  {
    "Iteration":141,
    "Value":36664.5569620253,
    "Agent":"C2D"
  },
  {
    "Iteration":142,
    "Value":37796.1038961039,
    "Agent":"C2D"
  },
  {
    "Iteration":143,
    "Value":36418.9873417722,
    "Agent":"C2D"
  },
  {
    "Iteration":144,
    "Value":38546.6666666667,
    "Agent":"C2D"
  },
  {
    "Iteration":145,
    "Value":40370.8333333333,
    "Agent":"C2D"
  },
  {
    "Iteration":146,
    "Value":37206.3291139241,
    "Agent":"C2D"
  },
  {
    "Iteration":147,
    "Value":37550.6493506493,
    "Agent":"C2D"
  },
  {
    "Iteration":148,
    "Value":37245.5696202532,
    "Agent":"C2D"
  },
  {
    "Iteration":149,
    "Value":38737.3333333333,
    "Agent":"C2D"
  },
  {
    "Iteration":150,
    "Value":36478.4810126582,
    "Agent":"C2D"
  },
  {
    "Iteration":151,
    "Value":34760.4938271605,
    "Agent":"C2D"
  },
  {
    "Iteration":152,
    "Value":35543.9024390244,
    "Agent":"C2D"
  },
  {
    "Iteration":153,
    "Value":37085.0,
    "Agent":"C2D"
  },
  {
    "Iteration":154,
    "Value":37514.1025641026,
    "Agent":"C2D"
  },
  {
    "Iteration":155,
    "Value":39378.0821917808,
    "Agent":"C2D"
  },
  {
    "Iteration":156,
    "Value":39047.3684210526,
    "Agent":"C2D"
  },
  {
    "Iteration":157,
    "Value":38801.3513513514,
    "Agent":"C2D"
  },
  {
    "Iteration":158,
    "Value":40326.3888888889,
    "Agent":"C2D"
  },
  {
    "Iteration":159,
    "Value":40640.2777777778,
    "Agent":"C2D"
  },
  {
    "Iteration":160,
    "Value":41030.985915493,
    "Agent":"C2D"
  },
  {
    "Iteration":161,
    "Value":40702.8169014084,
    "Agent":"C2D"
  },
  {
    "Iteration":162,
    "Value":42142.8571428571,
    "Agent":"C2D"
  },
  {
    "Iteration":163,
    "Value":40895.7142857143,
    "Agent":"C2D"
  },
  {
    "Iteration":164,
    "Value":40010.9589041096,
    "Agent":"C2D"
  },
  {
    "Iteration":165,
    "Value":41228.1690140845,
    "Agent":"C2D"
  },
  {
    "Iteration":166,
    "Value":40495.7746478873,
    "Agent":"C2D"
  },
  {
    "Iteration":167,
    "Value":38913.5135135135,
    "Agent":"C2D"
  },
  {
    "Iteration":168,
    "Value":41181.6901408451,
    "Agent":"C2D"
  },
  {
    "Iteration":169,
    "Value":39544.5945945946,
    "Agent":"C2D"
  },
  {
    "Iteration":170,
    "Value":37600.0,
    "Agent":"C2D"
  },
  {
    "Iteration":171,
    "Value":40305.6338028169,
    "Agent":"C2D"
  },
  {
    "Iteration":172,
    "Value":40063.8888888889,
    "Agent":"C2D"
  },
  {
    "Iteration":173,
    "Value":38978.3783783784,
    "Agent":"C2D"
  },
  {
    "Iteration":174,
    "Value":40272.602739726,
    "Agent":"C2D"
  },
  {
    "Iteration":175,
    "Value":36683.5443037975,
    "Agent":"C2D"
  },
  {
    "Iteration":176,
    "Value":39709.5890410959,
    "Agent":"C2D"
  },
  {
    "Iteration":177,
    "Value":41823.9436619718,
    "Agent":"C2D"
  },
  {
    "Iteration":178,
    "Value":37578.9473684211,
    "Agent":"C2D"
  },
  {
    "Iteration":179,
    "Value":38862.1621621622,
    "Agent":"C2D"
  },
  {
    "Iteration":180,
    "Value":36666.2337662338,
    "Agent":"C2D"
  },
  {
    "Iteration":181,
    "Value":38638.1578947368,
    "Agent":"C2D"
  },
  {
    "Iteration":182,
    "Value":39177.027027027,
    "Agent":"C2D"
  },
  {
    "Iteration":183,
    "Value":36715.0,
    "Agent":"C2D"
  },
  {
    "Iteration":184,
    "Value":40708.3333333333,
    "Agent":"C2D"
  },
  {
    "Iteration":185,
    "Value":42144.2857142857,
    "Agent":"C2D"
  },
  {
    "Iteration":186,
    "Value":38964.0,
    "Agent":"C2D"
  },
  {
    "Iteration":187,
    "Value":40761.1111111111,
    "Agent":"C2D"
  },
  {
    "Iteration":188,
    "Value":42236.231884058,
    "Agent":"C2D"
  },
  {
    "Iteration":189,
    "Value":38569.3333333333,
    "Agent":"C2D"
  },
  {
    "Iteration":190,
    "Value":39464.0,
    "Agent":"C2D"
  },
  {
    "Iteration":191,
    "Value":42823.5294117647,
    "Agent":"C2D"
  },
  {
    "Iteration":192,
    "Value":39726.0273972603,
    "Agent":"C2D"
  },
  {
    "Iteration":193,
    "Value":41701.4285714286,
    "Agent":"C2D"
  },
  {
    "Iteration":194,
    "Value":42828.9855072464,
    "Agent":"C2D"
  },
  {
    "Iteration":195,
    "Value":41487.1428571429,
    "Agent":"C2D"
  },
  {
    "Iteration":196,
    "Value":39558.904109589,
    "Agent":"C2D"
  },
  {
    "Iteration":197,
    "Value":40937.5,
    "Agent":"C2D"
  },
  {
    "Iteration":198,
    "Value":39635.6164383562,
    "Agent":"C2D"
  },
  {
    "Iteration":199,
    "Value":40145.9459459459,
    "Agent":"C2D"
  },
  {
    "Iteration":0,
    "Value":1192.8571428571,
    "Agent":"C2D"
  },
  {
    "Iteration":1,
    "Value":8169.2307692308,
    "Agent":"C2D"
  },
  {
    "Iteration":2,
    "Value":11743.7037037037,
    "Agent":"C2D"
  },
  {
    "Iteration":3,
    "Value":13543.8016528926,
    "Agent":"C2D"
  },
  {
    "Iteration":4,
    "Value":16034.7826086957,
    "Agent":"C2D"
  },
  {
    "Iteration":5,
    "Value":17718.018018018,
    "Agent":"C2D"
  },
  {
    "Iteration":6,
    "Value":19653.7037037037,
    "Agent":"C2D"
  },
  {
    "Iteration":7,
    "Value":21246.6019417476,
    "Agent":"C2D"
  },
  {
    "Iteration":8,
    "Value":20891.5887850467,
    "Agent":"C2D"
  },
  {
    "Iteration":9,
    "Value":20463.3928571429,
    "Agent":"C2D"
  },
  {
    "Iteration":10,
    "Value":22896.2264150943,
    "Agent":"C2D"
  },
  {
    "Iteration":11,
    "Value":25334.0206185567,
    "Agent":"C2D"
  },
  {
    "Iteration":12,
    "Value":25483.6734693878,
    "Agent":"C2D"
  },
  {
    "Iteration":13,
    "Value":25673.4693877551,
    "Agent":"C2D"
  },
  {
    "Iteration":14,
    "Value":25188.7755102041,
    "Agent":"C2D"
  },
  {
    "Iteration":15,
    "Value":25036.7346938776,
    "Agent":"C2D"
  },
  {
    "Iteration":16,
    "Value":27389.4736842105,
    "Agent":"C2D"
  },
  {
    "Iteration":17,
    "Value":26316.4948453608,
    "Agent":"C2D"
  },
  {
    "Iteration":18,
    "Value":27078.7234042553,
    "Agent":"C2D"
  },
  {
    "Iteration":19,
    "Value":26551.0416666667,
    "Agent":"C2D"
  },
  {
    "Iteration":20,
    "Value":27975.2688172043,
    "Agent":"C2D"
  },
  {
    "Iteration":21,
    "Value":27538.2978723404,
    "Agent":"C2D"
  },
  {
    "Iteration":22,
    "Value":28935.1648351648,
    "Agent":"C2D"
  },
  {
    "Iteration":23,
    "Value":26153.0612244898,
    "Agent":"C2D"
  },
  {
    "Iteration":24,
    "Value":26819.587628866,
    "Agent":"C2D"
  },
  {
    "Iteration":25,
    "Value":27451.5463917526,
    "Agent":"C2D"
  },
  {
    "Iteration":26,
    "Value":27239.5833333333,
    "Agent":"C2D"
  },
  {
    "Iteration":27,
    "Value":26296.0,
    "Agent":"C2D"
  },
  {
    "Iteration":28,
    "Value":28611.8279569892,
    "Agent":"C2D"
  },
  {
    "Iteration":29,
    "Value":29590.2173913043,
    "Agent":"C2D"
  },
  {
    "Iteration":30,
    "Value":30111.1111111111,
    "Agent":"C2D"
  },
  {
    "Iteration":31,
    "Value":29565.9340659341,
    "Agent":"C2D"
  },
  {
    "Iteration":32,
    "Value":29670.3296703297,
    "Agent":"C2D"
  },
  {
    "Iteration":33,
    "Value":30663.6363636364,
    "Agent":"C2D"
  },
  {
    "Iteration":34,
    "Value":28202.0833333333,
    "Agent":"C2D"
  },
  {
    "Iteration":35,
    "Value":29066.3043478261,
    "Agent":"C2D"
  },
  {
    "Iteration":36,
    "Value":28175.7894736842,
    "Agent":"C2D"
  },
  {
    "Iteration":37,
    "Value":30095.6043956044,
    "Agent":"C2D"
  },
  {
    "Iteration":38,
    "Value":31266.2921348315,
    "Agent":"C2D"
  },
  {
    "Iteration":39,
    "Value":29355.9139784946,
    "Agent":"C2D"
  },
  {
    "Iteration":40,
    "Value":29219.3548387097,
    "Agent":"C2D"
  },
  {
    "Iteration":41,
    "Value":30781.1111111111,
    "Agent":"C2D"
  },
  {
    "Iteration":42,
    "Value":31061.797752809,
    "Agent":"C2D"
  },
  {
    "Iteration":43,
    "Value":29097.8494623656,
    "Agent":"C2D"
  },
  {
    "Iteration":44,
    "Value":30537.0786516854,
    "Agent":"C2D"
  },
  {
    "Iteration":45,
    "Value":31565.9090909091,
    "Agent":"C2D"
  },
  {
    "Iteration":46,
    "Value":31303.3707865169,
    "Agent":"C2D"
  },
  {
    "Iteration":47,
    "Value":30561.1111111111,
    "Agent":"C2D"
  },
  {
    "Iteration":48,
    "Value":33197.6470588235,
    "Agent":"C2D"
  },
  {
    "Iteration":49,
    "Value":31461.1111111111,
    "Agent":"C2D"
  },
  {
    "Iteration":50,
    "Value":31221.5909090909,
    "Agent":"C2D"
  },
  {
    "Iteration":51,
    "Value":31673.8636363636,
    "Agent":"C2D"
  },
  {
    "Iteration":52,
    "Value":33162.3529411765,
    "Agent":"C2D"
  },
  {
    "Iteration":53,
    "Value":33247.0588235294,
    "Agent":"C2D"
  },
  {
    "Iteration":54,
    "Value":33601.1904761905,
    "Agent":"C2D"
  },
  {
    "Iteration":55,
    "Value":31695.4022988506,
    "Agent":"C2D"
  },
  {
    "Iteration":56,
    "Value":32372.0930232558,
    "Agent":"C2D"
  },
  {
    "Iteration":57,
    "Value":32817.4418604651,
    "Agent":"C2D"
  },
  {
    "Iteration":58,
    "Value":30352.1739130435,
    "Agent":"C2D"
  },
  {
    "Iteration":59,
    "Value":31300.0,
    "Agent":"C2D"
  },
  {
    "Iteration":60,
    "Value":31565.1685393258,
    "Agent":"C2D"
  },
  {
    "Iteration":61,
    "Value":30642.2222222222,
    "Agent":"C2D"
  },
  {
    "Iteration":62,
    "Value":31739.7727272727,
    "Agent":"C2D"
  },
  {
    "Iteration":63,
    "Value":30770.1149425287,
    "Agent":"C2D"
  },
  {
    "Iteration":64,
    "Value":31361.797752809,
    "Agent":"C2D"
  },
  {
    "Iteration":65,
    "Value":33275.5813953488,
    "Agent":"C2D"
  },
  {
    "Iteration":66,
    "Value":32488.6363636364,
    "Agent":"C2D"
  },
  {
    "Iteration":67,
    "Value":31094.5054945055,
    "Agent":"C2D"
  },
  {
    "Iteration":68,
    "Value":31715.9090909091,
    "Agent":"C2D"
  },
  {
    "Iteration":69,
    "Value":31455.0561797753,
    "Agent":"C2D"
  },
  {
    "Iteration":70,
    "Value":31956.3218390805,
    "Agent":"C2D"
  },
  {
    "Iteration":71,
    "Value":32806.976744186,
    "Agent":"C2D"
  },
  {
    "Iteration":72,
    "Value":36494.8717948718,
    "Agent":"C2D"
  },
  {
    "Iteration":73,
    "Value":32405.8139534884,
    "Agent":"C2D"
  },
  {
    "Iteration":74,
    "Value":35570.3703703704,
    "Agent":"C2D"
  },
  {
    "Iteration":75,
    "Value":34668.2926829268,
    "Agent":"C2D"
  },
  {
    "Iteration":76,
    "Value":32888.3720930233,
    "Agent":"C2D"
  },
  {
    "Iteration":77,
    "Value":33016.2790697674,
    "Agent":"C2D"
  },
  {
    "Iteration":78,
    "Value":36128.2051282051,
    "Agent":"C2D"
  },
  {
    "Iteration":79,
    "Value":35095.1219512195,
    "Agent":"C2D"
  },
  {
    "Iteration":80,
    "Value":36579.4871794872,
    "Agent":"C2D"
  },
  {
    "Iteration":81,
    "Value":34692.5925925926,
    "Agent":"C2D"
  },
  {
    "Iteration":82,
    "Value":36231.25,
    "Agent":"C2D"
  },
  {
    "Iteration":83,
    "Value":35780.2469135802,
    "Agent":"C2D"
  },
  {
    "Iteration":84,
    "Value":35284.8101265823,
    "Agent":"C2D"
  },
  {
    "Iteration":85,
    "Value":37098.7012987013,
    "Agent":"C2D"
  },
  {
    "Iteration":86,
    "Value":36705.1282051282,
    "Agent":"C2D"
  },
  {
    "Iteration":87,
    "Value":34196.2962962963,
    "Agent":"C2D"
  },
  {
    "Iteration":88,
    "Value":36027.5,
    "Agent":"C2D"
  },
  {
    "Iteration":89,
    "Value":34787.8048780488,
    "Agent":"C2D"
  },
  {
    "Iteration":90,
    "Value":37911.8421052632,
    "Agent":"C2D"
  },
  {
    "Iteration":91,
    "Value":34991.4634146341,
    "Agent":"C2D"
  },
  {
    "Iteration":92,
    "Value":36051.2820512821,
    "Agent":"C2D"
  },
  {
    "Iteration":93,
    "Value":36108.8607594937,
    "Agent":"C2D"
  },
  {
    "Iteration":94,
    "Value":38779.7297297297,
    "Agent":"C2D"
  },
  {
    "Iteration":95,
    "Value":38568.9189189189,
    "Agent":"C2D"
  },
  {
    "Iteration":96,
    "Value":37325.0,
    "Agent":"C2D"
  },
  {
    "Iteration":97,
    "Value":38798.6486486486,
    "Agent":"C2D"
  },
  {
    "Iteration":98,
    "Value":35430.0,
    "Agent":"C2D"
  },
  {
    "Iteration":99,
    "Value":38791.8918918919,
    "Agent":"C2D"
  },
  {
    "Iteration":100,
    "Value":37897.4025974026,
    "Agent":"C2D"
  },
  {
    "Iteration":101,
    "Value":36136.7088607595,
    "Agent":"C2D"
  },
  {
    "Iteration":102,
    "Value":37929.3333333333,
    "Agent":"C2D"
  },
  {
    "Iteration":103,
    "Value":37264.4736842105,
    "Agent":"C2D"
  },
  {
    "Iteration":104,
    "Value":38493.4210526316,
    "Agent":"C2D"
  },
  {
    "Iteration":105,
    "Value":37653.2467532468,
    "Agent":"C2D"
  },
  {
    "Iteration":106,
    "Value":39108.2191780822,
    "Agent":"C2D"
  },
  {
    "Iteration":107,
    "Value":37340.5405405405,
    "Agent":"C2D"
  },
  {
    "Iteration":108,
    "Value":38537.8378378378,
    "Agent":"C2D"
  },
  {
    "Iteration":109,
    "Value":37462.1621621622,
    "Agent":"C2D"
  },
  {
    "Iteration":110,
    "Value":38652.0547945205,
    "Agent":"C2D"
  },
  {
    "Iteration":111,
    "Value":39197.3333333333,
    "Agent":"C2D"
  },
  {
    "Iteration":112,
    "Value":37837.8378378378,
    "Agent":"C2D"
  },
  {
    "Iteration":113,
    "Value":39935.6164383562,
    "Agent":"C2D"
  },
  {
    "Iteration":114,
    "Value":38867.1232876712,
    "Agent":"C2D"
  },
  {
    "Iteration":115,
    "Value":40273.6111111111,
    "Agent":"C2D"
  },
  {
    "Iteration":116,
    "Value":38842.6666666667,
    "Agent":"C2D"
  },
  {
    "Iteration":117,
    "Value":40821.4285714286,
    "Agent":"C2D"
  },
  {
    "Iteration":118,
    "Value":39393.0555555556,
    "Agent":"C2D"
  },
  {
    "Iteration":119,
    "Value":41708.6956521739,
    "Agent":"C2D"
  },
  {
    "Iteration":120,
    "Value":40028.7671232877,
    "Agent":"C2D"
  },
  {
    "Iteration":121,
    "Value":41447.0588235294,
    "Agent":"C2D"
  },
  {
    "Iteration":122,
    "Value":38071.6216216216,
    "Agent":"C2D"
  },
  {
    "Iteration":123,
    "Value":39550.0,
    "Agent":"C2D"
  },
  {
    "Iteration":124,
    "Value":39280.5555555556,
    "Agent":"C2D"
  },
  {
    "Iteration":125,
    "Value":41933.8235294118,
    "Agent":"C2D"
  },
  {
    "Iteration":126,
    "Value":40052.1739130435,
    "Agent":"C2D"
  },
  {
    "Iteration":127,
    "Value":41190.0,
    "Agent":"C2D"
  },
  {
    "Iteration":128,
    "Value":38769.014084507,
    "Agent":"C2D"
  },
  {
    "Iteration":129,
    "Value":41328.9855072464,
    "Agent":"C2D"
  },
  {
    "Iteration":130,
    "Value":39057.5342465753,
    "Agent":"C2D"
  },
  {
    "Iteration":131,
    "Value":41434.7826086957,
    "Agent":"C2D"
  },
  {
    "Iteration":132,
    "Value":37859.4594594595,
    "Agent":"C2D"
  },
  {
    "Iteration":133,
    "Value":39378.0821917808,
    "Agent":"C2D"
  },
  {
    "Iteration":134,
    "Value":39638.8888888889,
    "Agent":"C2D"
  },
  {
    "Iteration":135,
    "Value":39138.3561643836,
    "Agent":"C2D"
  },
  {
    "Iteration":136,
    "Value":38625.6756756757,
    "Agent":"C2D"
  },
  {
    "Iteration":137,
    "Value":40963.768115942,
    "Agent":"C2D"
  },
  {
    "Iteration":138,
    "Value":40105.5555555556,
    "Agent":"C2D"
  },
  {
    "Iteration":139,
    "Value":40808.6956521739,
    "Agent":"C2D"
  },
  {
    "Iteration":140,
    "Value":40001.3888888889,
    "Agent":"C2D"
  },
  {
    "Iteration":141,
    "Value":38797.2222222222,
    "Agent":"C2D"
  },
  {
    "Iteration":142,
    "Value":40370.0,
    "Agent":"C2D"
  },
  {
    "Iteration":143,
    "Value":43105.9701492537,
    "Agent":"C2D"
  },
  {
    "Iteration":144,
    "Value":41895.652173913,
    "Agent":"C2D"
  },
  {
    "Iteration":145,
    "Value":41818.8405797101,
    "Agent":"C2D"
  },
  {
    "Iteration":146,
    "Value":38990.2777777778,
    "Agent":"C2D"
  },
  {
    "Iteration":147,
    "Value":42642.6470588235,
    "Agent":"C2D"
  },
  {
    "Iteration":148,
    "Value":41580.0,
    "Agent":"C2D"
  },
  {
    "Iteration":149,
    "Value":42139.1304347826,
    "Agent":"C2D"
  },
  {
    "Iteration":150,
    "Value":39734.7222222222,
    "Agent":"C2D"
  },
  {
    "Iteration":151,
    "Value":39315.0684931507,
    "Agent":"C2D"
  },
  {
    "Iteration":152,
    "Value":43504.5454545455,
    "Agent":"C2D"
  },
  {
    "Iteration":153,
    "Value":40734.2857142857,
    "Agent":"C2D"
  },
  {
    "Iteration":154,
    "Value":38708.1081081081,
    "Agent":"C2D"
  },
  {
    "Iteration":155,
    "Value":37498.6666666667,
    "Agent":"C2D"
  },
  {
    "Iteration":156,
    "Value":45184.8484848485,
    "Agent":"C2D"
  },
  {
    "Iteration":157,
    "Value":40854.9295774648,
    "Agent":"C2D"
  },
  {
    "Iteration":158,
    "Value":41519.1176470588,
    "Agent":"C2D"
  },
  {
    "Iteration":159,
    "Value":43268.6567164179,
    "Agent":"C2D"
  },
  {
    "Iteration":160,
    "Value":42602.9850746269,
    "Agent":"C2D"
  },
  {
    "Iteration":161,
    "Value":39804.1095890411,
    "Agent":"C2D"
  },
  {
    "Iteration":162,
    "Value":42713.2352941177,
    "Agent":"C2D"
  },
  {
    "Iteration":163,
    "Value":41078.8732394366,
    "Agent":"C2D"
  },
  {
    "Iteration":164,
    "Value":41101.4285714286,
    "Agent":"C2D"
  },
  {
    "Iteration":165,
    "Value":43713.8461538462,
    "Agent":"C2D"
  },
  {
    "Iteration":166,
    "Value":41195.7142857143,
    "Agent":"C2D"
  },
  {
    "Iteration":167,
    "Value":43580.8823529412,
    "Agent":"C2D"
  },
  {
    "Iteration":168,
    "Value":41611.5942028986,
    "Agent":"C2D"
  },
  {
    "Iteration":169,
    "Value":39456.1643835616,
    "Agent":"C2D"
  },
  {
    "Iteration":170,
    "Value":44421.2121212121,
    "Agent":"C2D"
  },
  {
    "Iteration":171,
    "Value":41997.1014492754,
    "Agent":"C2D"
  },
  {
    "Iteration":172,
    "Value":40041.6666666667,
    "Agent":"C2D"
  },
  {
    "Iteration":173,
    "Value":41940.5797101449,
    "Agent":"C2D"
  },
  {
    "Iteration":174,
    "Value":42079.7101449275,
    "Agent":"C2D"
  },
  {
    "Iteration":175,
    "Value":43925.7575757576,
    "Agent":"C2D"
  },
  {
    "Iteration":176,
    "Value":43228.7878787879,
    "Agent":"C2D"
  },
  {
    "Iteration":177,
    "Value":41992.8571428571,
    "Agent":"C2D"
  },
  {
    "Iteration":178,
    "Value":40183.0985915493,
    "Agent":"C2D"
  },
  {
    "Iteration":179,
    "Value":41652.8571428571,
    "Agent":"C2D"
  },
  {
    "Iteration":180,
    "Value":41600.0,
    "Agent":"C2D"
  },
  {
    "Iteration":181,
    "Value":43250.0,
    "Agent":"C2D"
  },
  {
    "Iteration":182,
    "Value":41957.3529411765,
    "Agent":"C2D"
  },
  {
    "Iteration":183,
    "Value":42878.2608695652,
    "Agent":"C2D"
  },
  {
    "Iteration":184,
    "Value":42970.5882352941,
    "Agent":"C2D"
  },
  {
    "Iteration":185,
    "Value":42338.2352941177,
    "Agent":"C2D"
  },
  {
    "Iteration":186,
    "Value":46468.253968254,
    "Agent":"C2D"
  },
  {
    "Iteration":187,
    "Value":40512.5,
    "Agent":"C2D"
  },
  {
    "Iteration":188,
    "Value":42302.9411764706,
    "Agent":"C2D"
  },
  {
    "Iteration":189,
    "Value":41708.4507042254,
    "Agent":"C2D"
  },
  {
    "Iteration":190,
    "Value":44563.6363636364,
    "Agent":"C2D"
  },
  {
    "Iteration":191,
    "Value":42776.4705882353,
    "Agent":"C2D"
  },
  {
    "Iteration":192,
    "Value":43342.4242424242,
    "Agent":"C2D"
  },
  {
    "Iteration":193,
    "Value":44653.8461538462,
    "Agent":"C2D"
  },
  {
    "Iteration":194,
    "Value":44718.4615384615,
    "Agent":"C2D"
  },
  {
    "Iteration":195,
    "Value":44269.696969697,
    "Agent":"C2D"
  },
  {
    "Iteration":196,
    "Value":41736.231884058,
    "Agent":"C2D"
  },
  {
    "Iteration":197,
    "Value":44745.4545454545,
    "Agent":"C2D"
  },
  {
    "Iteration":198,
    "Value":42297.0588235294,
    "Agent":"C2D"
  },
  {
    "Iteration":199,
    "Value":40112.8571428571,
    "Agent":"C2D"
  },
  {
    "Iteration":0,
    "Value":2317.6211453744,
    "Agent":"C2D"
  },
  {
    "Iteration":1,
    "Value":11386.4285714286,
    "Agent":"C2D"
  },
  {
    "Iteration":2,
    "Value":11482.2695035461,
    "Agent":"C2D"
  },
  {
    "Iteration":3,
    "Value":13678.5714285714,
    "Agent":"C2D"
  },
  {
    "Iteration":4,
    "Value":18060.1851851852,
    "Agent":"C2D"
  },
  {
    "Iteration":5,
    "Value":19706.4220183486,
    "Agent":"C2D"
  },
  {
    "Iteration":6,
    "Value":19603.6363636364,
    "Agent":"C2D"
  },
  {
    "Iteration":7,
    "Value":21429.8076923077,
    "Agent":"C2D"
  },
  {
    "Iteration":8,
    "Value":21004.9019607843,
    "Agent":"C2D"
  },
  {
    "Iteration":9,
    "Value":21767.3267326733,
    "Agent":"C2D"
  },
  {
    "Iteration":10,
    "Value":20625.0,
    "Agent":"C2D"
  },
  {
    "Iteration":11,
    "Value":22510.6796116505,
    "Agent":"C2D"
  },
  {
    "Iteration":12,
    "Value":21693.3333333333,
    "Agent":"C2D"
  },
  {
    "Iteration":13,
    "Value":22348.0392156863,
    "Agent":"C2D"
  },
  {
    "Iteration":14,
    "Value":23534.693877551,
    "Agent":"C2D"
  },
  {
    "Iteration":15,
    "Value":22239.8058252427,
    "Agent":"C2D"
  },
  {
    "Iteration":16,
    "Value":23251.0,
    "Agent":"C2D"
  },
  {
    "Iteration":17,
    "Value":25049.0,
    "Agent":"C2D"
  },
  {
    "Iteration":18,
    "Value":25341.4141414141,
    "Agent":"C2D"
  },
  {
    "Iteration":19,
    "Value":24741.0,
    "Agent":"C2D"
  },
  {
    "Iteration":20,
    "Value":26254.1666666667,
    "Agent":"C2D"
  },
  {
    "Iteration":21,
    "Value":25351.5151515152,
    "Agent":"C2D"
  },
  {
    "Iteration":22,
    "Value":26020.618556701,
    "Agent":"C2D"
  },
  {
    "Iteration":23,
    "Value":25150.4950495049,
    "Agent":"C2D"
  },
  {
    "Iteration":24,
    "Value":25701.0309278351,
    "Agent":"C2D"
  },
  {
    "Iteration":25,
    "Value":26678.3505154639,
    "Agent":"C2D"
  },
  {
    "Iteration":26,
    "Value":24947.0,
    "Agent":"C2D"
  },
  {
    "Iteration":27,
    "Value":25961.8556701031,
    "Agent":"C2D"
  },
  {
    "Iteration":28,
    "Value":24990.099009901,
    "Agent":"C2D"
  },
  {
    "Iteration":29,
    "Value":27280.6451612903,
    "Agent":"C2D"
  },
  {
    "Iteration":30,
    "Value":25779.381443299,
    "Agent":"C2D"
  },
  {
    "Iteration":31,
    "Value":25206.0,
    "Agent":"C2D"
  },
  {
    "Iteration":32,
    "Value":24896.0396039604,
    "Agent":"C2D"
  },
  {
    "Iteration":33,
    "Value":24862.3762376238,
    "Agent":"C2D"
  },
  {
    "Iteration":34,
    "Value":27070.8333333333,
    "Agent":"C2D"
  },
  {
    "Iteration":35,
    "Value":24775.2475247525,
    "Agent":"C2D"
  },
  {
    "Iteration":36,
    "Value":25682.6530612245,
    "Agent":"C2D"
  },
  {
    "Iteration":37,
    "Value":24800.0,
    "Agent":"C2D"
  },
  {
    "Iteration":38,
    "Value":25864.6464646465,
    "Agent":"C2D"
  },
  {
    "Iteration":39,
    "Value":25506.1224489796,
    "Agent":"C2D"
  },
  {
    "Iteration":40,
    "Value":26131.6326530612,
    "Agent":"C2D"
  },
  {
    "Iteration":41,
    "Value":25952.5773195876,
    "Agent":"C2D"
  },
  {
    "Iteration":42,
    "Value":25386.7346938776,
    "Agent":"C2D"
  },
  {
    "Iteration":43,
    "Value":24790.9090909091,
    "Agent":"C2D"
  },
  {
    "Iteration":44,
    "Value":26282.2916666667,
    "Agent":"C2D"
  },
  {
    "Iteration":45,
    "Value":25710.2040816327,
    "Agent":"C2D"
  },
  {
    "Iteration":46,
    "Value":26388.6597938144,
    "Agent":"C2D"
  },
  {
    "Iteration":47,
    "Value":26346.875,
    "Agent":"C2D"
  },
  {
    "Iteration":48,
    "Value":26359.793814433,
    "Agent":"C2D"
  },
  {
    "Iteration":49,
    "Value":26980.6451612903,
    "Agent":"C2D"
  },
  {
    "Iteration":50,
    "Value":24888.1188118812,
    "Agent":"C2D"
  },
  {
    "Iteration":51,
    "Value":25451.5151515152,
    "Agent":"C2D"
  },
  {
    "Iteration":52,
    "Value":22731.4285714286,
    "Agent":"C2D"
  },
  {
    "Iteration":53,
    "Value":25767.3469387755,
    "Agent":"C2D"
  },
  {
    "Iteration":54,
    "Value":25462.0,
    "Agent":"C2D"
  },
  {
    "Iteration":55,
    "Value":26400.0,
    "Agent":"C2D"
  },
  {
    "Iteration":56,
    "Value":26671.7171717172,
    "Agent":"C2D"
  },
  {
    "Iteration":57,
    "Value":26334.0206185567,
    "Agent":"C2D"
  },
  {
    "Iteration":58,
    "Value":28148.4210526316,
    "Agent":"C2D"
  },
  {
    "Iteration":59,
    "Value":27498.9361702128,
    "Agent":"C2D"
  },
  {
    "Iteration":60,
    "Value":27872.0430107527,
    "Agent":"C2D"
  },
  {
    "Iteration":61,
    "Value":30486.2068965517,
    "Agent":"C2D"
  },
  {
    "Iteration":62,
    "Value":29240.6593406593,
    "Agent":"C2D"
  },
  {
    "Iteration":63,
    "Value":29008.6021505376,
    "Agent":"C2D"
  },
  {
    "Iteration":64,
    "Value":28425.2631578947,
    "Agent":"C2D"
  },
  {
    "Iteration":65,
    "Value":29895.6043956044,
    "Agent":"C2D"
  },
  {
    "Iteration":66,
    "Value":30390.9090909091,
    "Agent":"C2D"
  },
  {
    "Iteration":67,
    "Value":30865.1685393258,
    "Agent":"C2D"
  },
  {
    "Iteration":68,
    "Value":31281.3953488372,
    "Agent":"C2D"
  },
  {
    "Iteration":69,
    "Value":32215.4761904762,
    "Agent":"C2D"
  },
  {
    "Iteration":70,
    "Value":31900.0,
    "Agent":"C2D"
  },
  {
    "Iteration":71,
    "Value":30434.0909090909,
    "Agent":"C2D"
  },
  {
    "Iteration":72,
    "Value":30388.8888888889,
    "Agent":"C2D"
  },
  {
    "Iteration":73,
    "Value":32052.3255813953,
    "Agent":"C2D"
  },
  {
    "Iteration":74,
    "Value":34400.0,
    "Agent":"C2D"
  },
  {
    "Iteration":75,
    "Value":32312.9411764706,
    "Agent":"C2D"
  },
  {
    "Iteration":76,
    "Value":34660.0,
    "Agent":"C2D"
  },
  {
    "Iteration":77,
    "Value":34753.164556962,
    "Agent":"C2D"
  },
  {
    "Iteration":78,
    "Value":33236.1445783133,
    "Agent":"C2D"
  },
  {
    "Iteration":79,
    "Value":32610.7142857143,
    "Agent":"C2D"
  },
  {
    "Iteration":80,
    "Value":32066.2790697674,
    "Agent":"C2D"
  },
  {
    "Iteration":81,
    "Value":31084.7058823529,
    "Agent":"C2D"
  },
  {
    "Iteration":82,
    "Value":31544.7058823529,
    "Agent":"C2D"
  },
  {
    "Iteration":83,
    "Value":34687.5,
    "Agent":"C2D"
  },
  {
    "Iteration":84,
    "Value":34106.4102564103,
    "Agent":"C2D"
  },
  {
    "Iteration":85,
    "Value":33393.9759036145,
    "Agent":"C2D"
  },
  {
    "Iteration":86,
    "Value":33374.3902439024,
    "Agent":"C2D"
  },
  {
    "Iteration":87,
    "Value":37098.6486486486,
    "Agent":"C2D"
  },
  {
    "Iteration":88,
    "Value":35306.25,
    "Agent":"C2D"
  },
  {
    "Iteration":89,
    "Value":36350.0,
    "Agent":"C2D"
  },
  {
    "Iteration":90,
    "Value":34945.0,
    "Agent":"C2D"
  },
  {
    "Iteration":91,
    "Value":33225.0,
    "Agent":"C2D"
  },
  {
    "Iteration":92,
    "Value":33998.7654320988,
    "Agent":"C2D"
  },
  {
    "Iteration":93,
    "Value":33397.5903614458,
    "Agent":"C2D"
  },
  {
    "Iteration":94,
    "Value":35964.9350649351,
    "Agent":"C2D"
  },
  {
    "Iteration":95,
    "Value":37301.3698630137,
    "Agent":"C2D"
  },
  {
    "Iteration":96,
    "Value":33524.3902439024,
    "Agent":"C2D"
  },
  {
    "Iteration":97,
    "Value":36049.3506493507,
    "Agent":"C2D"
  },
  {
    "Iteration":98,
    "Value":36197.4358974359,
    "Agent":"C2D"
  },
  {
    "Iteration":99,
    "Value":36456.5789473684,
    "Agent":"C2D"
  },
  {
    "Iteration":100,
    "Value":36800.0,
    "Agent":"C2D"
  },
  {
    "Iteration":101,
    "Value":36834.2105263158,
    "Agent":"C2D"
  },
  {
    "Iteration":102,
    "Value":36481.5789473684,
    "Agent":"C2D"
  },
  {
    "Iteration":103,
    "Value":35480.7692307692,
    "Agent":"C2D"
  },
  {
    "Iteration":104,
    "Value":35373.417721519,
    "Agent":"C2D"
  },
  {
    "Iteration":105,
    "Value":33789.0243902439,
    "Agent":"C2D"
  },
  {
    "Iteration":106,
    "Value":38324.3243243243,
    "Agent":"C2D"
  },
  {
    "Iteration":107,
    "Value":37135.5263157895,
    "Agent":"C2D"
  },
  {
    "Iteration":108,
    "Value":33833.3333333333,
    "Agent":"C2D"
  },
  {
    "Iteration":109,
    "Value":35883.3333333333,
    "Agent":"C2D"
  },
  {
    "Iteration":110,
    "Value":34901.25,
    "Agent":"C2D"
  },
  {
    "Iteration":111,
    "Value":35017.7215189873,
    "Agent":"C2D"
  },
  {
    "Iteration":112,
    "Value":36350.6493506493,
    "Agent":"C2D"
  },
  {
    "Iteration":113,
    "Value":37243.4210526316,
    "Agent":"C2D"
  },
  {
    "Iteration":114,
    "Value":35614.2857142857,
    "Agent":"C2D"
  },
  {
    "Iteration":115,
    "Value":35701.2658227848,
    "Agent":"C2D"
  },
  {
    "Iteration":116,
    "Value":33274.6987951807,
    "Agent":"C2D"
  },
  {
    "Iteration":117,
    "Value":35340.5063291139,
    "Agent":"C2D"
  },
  {
    "Iteration":118,
    "Value":34713.5802469136,
    "Agent":"C2D"
  },
  {
    "Iteration":119,
    "Value":34993.8271604938,
    "Agent":"C2D"
  },
  {
    "Iteration":120,
    "Value":35150.0,
    "Agent":"C2D"
  },
  {
    "Iteration":121,
    "Value":32684.7058823529,
    "Agent":"C2D"
  },
  {
    "Iteration":122,
    "Value":35805.0632911392,
    "Agent":"C2D"
  },
  {
    "Iteration":123,
    "Value":35718.9873417722,
    "Agent":"C2D"
  },
  {
    "Iteration":124,
    "Value":36011.5384615385,
    "Agent":"C2D"
  },
  {
    "Iteration":125,
    "Value":36793.3333333333,
    "Agent":"C2D"
  },
  {
    "Iteration":126,
    "Value":36901.3157894737,
    "Agent":"C2D"
  },
  {
    "Iteration":127,
    "Value":35500.0,
    "Agent":"C2D"
  },
  {
    "Iteration":128,
    "Value":35998.7012987013,
    "Agent":"C2D"
  },
  {
    "Iteration":129,
    "Value":37789.4736842105,
    "Agent":"C2D"
  },
  {
    "Iteration":130,
    "Value":36114.2857142857,
    "Agent":"C2D"
  },
  {
    "Iteration":131,
    "Value":36032.4675324675,
    "Agent":"C2D"
  },
  {
    "Iteration":132,
    "Value":34893.8271604938,
    "Agent":"C2D"
  },
  {
    "Iteration":133,
    "Value":33501.1904761905,
    "Agent":"C2D"
  },
  {
    "Iteration":134,
    "Value":35316.049382716,
    "Agent":"C2D"
  },
  {
    "Iteration":135,
    "Value":33989.0243902439,
    "Agent":"C2D"
  },
  {
    "Iteration":136,
    "Value":32255.2941176471,
    "Agent":"C2D"
  },
  {
    "Iteration":137,
    "Value":36612.8205128205,
    "Agent":"C2D"
  },
  {
    "Iteration":138,
    "Value":37685.3333333333,
    "Agent":"C2D"
  },
  {
    "Iteration":139,
    "Value":36473.0769230769,
    "Agent":"C2D"
  },
  {
    "Iteration":140,
    "Value":35345.5696202532,
    "Agent":"C2D"
  },
  {
    "Iteration":141,
    "Value":35306.1728395062,
    "Agent":"C2D"
  },
  {
    "Iteration":142,
    "Value":34246.3414634146,
    "Agent":"C2D"
  },
  {
    "Iteration":143,
    "Value":34449.3670886076,
    "Agent":"C2D"
  },
  {
    "Iteration":144,
    "Value":35300.0,
    "Agent":"C2D"
  },
  {
    "Iteration":145,
    "Value":35546.1538461538,
    "Agent":"C2D"
  },
  {
    "Iteration":146,
    "Value":32294.1860465116,
    "Agent":"C2D"
  },
  {
    "Iteration":147,
    "Value":38256.9444444444,
    "Agent":"C2D"
  },
  {
    "Iteration":148,
    "Value":36184.8101265823,
    "Agent":"C2D"
  },
  {
    "Iteration":149,
    "Value":37750.6666666667,
    "Agent":"C2D"
  },
  {
    "Iteration":150,
    "Value":35724.0506329114,
    "Agent":"C2D"
  },
  {
    "Iteration":151,
    "Value":35722.7848101266,
    "Agent":"C2D"
  },
  {
    "Iteration":152,
    "Value":35703.75,
    "Agent":"C2D"
  },
  {
    "Iteration":153,
    "Value":34792.5925925926,
    "Agent":"C2D"
  },
  {
    "Iteration":154,
    "Value":34720.987654321,
    "Agent":"C2D"
  },
  {
    "Iteration":155,
    "Value":35245.6790123457,
    "Agent":"C2D"
  },
  {
    "Iteration":156,
    "Value":35700.0,
    "Agent":"C2D"
  },
  {
    "Iteration":157,
    "Value":36592.2077922078,
    "Agent":"C2D"
  },
  {
    "Iteration":158,
    "Value":33491.6666666667,
    "Agent":"C2D"
  },
  {
    "Iteration":159,
    "Value":35897.4358974359,
    "Agent":"C2D"
  },
  {
    "Iteration":160,
    "Value":37006.5789473684,
    "Agent":"C2D"
  },
  {
    "Iteration":161,
    "Value":37493.4210526316,
    "Agent":"C2D"
  },
  {
    "Iteration":162,
    "Value":37324.6753246753,
    "Agent":"C2D"
  },
  {
    "Iteration":163,
    "Value":37265.7894736842,
    "Agent":"C2D"
  },
  {
    "Iteration":164,
    "Value":35601.2658227848,
    "Agent":"C2D"
  },
  {
    "Iteration":165,
    "Value":36062.3376623377,
    "Agent":"C2D"
  },
  {
    "Iteration":166,
    "Value":35892.4050632911,
    "Agent":"C2D"
  },
  {
    "Iteration":167,
    "Value":35175.9493670886,
    "Agent":"C2D"
  },
  {
    "Iteration":168,
    "Value":37395.9459459459,
    "Agent":"C2D"
  },
  {
    "Iteration":169,
    "Value":36692.1052631579,
    "Agent":"C2D"
  },
  {
    "Iteration":170,
    "Value":35277.2151898734,
    "Agent":"C2D"
  },
  {
    "Iteration":171,
    "Value":35180.0,
    "Agent":"C2D"
  },
  {
    "Iteration":172,
    "Value":36992.2077922078,
    "Agent":"C2D"
  },
  {
    "Iteration":173,
    "Value":37628.0,
    "Agent":"C2D"
  },
  {
    "Iteration":174,
    "Value":39282.1917808219,
    "Agent":"C2D"
  },
  {
    "Iteration":175,
    "Value":38884.9315068493,
    "Agent":"C2D"
  },
  {
    "Iteration":176,
    "Value":36520.7792207792,
    "Agent":"C2D"
  },
  {
    "Iteration":177,
    "Value":38031.5789473684,
    "Agent":"C2D"
  },
  {
    "Iteration":178,
    "Value":37077.9220779221,
    "Agent":"C2D"
  },
  {
    "Iteration":179,
    "Value":37306.5789473684,
    "Agent":"C2D"
  },
  {
    "Iteration":180,
    "Value":37513.3333333333,
    "Agent":"C2D"
  },
  {
    "Iteration":181,
    "Value":40474.2857142857,
    "Agent":"C2D"
  },
  {
    "Iteration":182,
    "Value":39897.2222222222,
    "Agent":"C2D"
  },
  {
    "Iteration":183,
    "Value":39167.1232876712,
    "Agent":"C2D"
  },
  {
    "Iteration":184,
    "Value":37202.5641025641,
    "Agent":"C2D"
  },
  {
    "Iteration":185,
    "Value":38047.2972972973,
    "Agent":"C2D"
  },
  {
    "Iteration":186,
    "Value":40098.5915492958,
    "Agent":"C2D"
  },
  {
    "Iteration":187,
    "Value":39970.0,
    "Agent":"C2D"
  },
  {
    "Iteration":188,
    "Value":40830.985915493,
    "Agent":"C2D"
  },
  {
    "Iteration":189,
    "Value":38072.0,
    "Agent":"C2D"
  },
  {
    "Iteration":190,
    "Value":38733.7837837838,
    "Agent":"C2D"
  },
  {
    "Iteration":191,
    "Value":38601.3698630137,
    "Agent":"C2D"
  },
  {
    "Iteration":192,
    "Value":38924.6575342466,
    "Agent":"C2D"
  },
  {
    "Iteration":193,
    "Value":39493.1506849315,
    "Agent":"C2D"
  },
  {
    "Iteration":194,
    "Value":41284.2857142857,
    "Agent":"C2D"
  },
  {
    "Iteration":195,
    "Value":39466.1971830986,
    "Agent":"C2D"
  },
  {
    "Iteration":196,
    "Value":38656.9444444444,
    "Agent":"C2D"
  },
  {
    "Iteration":197,
    "Value":40270.8333333333,
    "Agent":"C2D"
  },
  {
    "Iteration":198,
    "Value":41553.6231884058,
    "Agent":"C2D"
  },
  {
    "Iteration":199,
    "Value":39616.9014084507,
    "Agent":"C2D"
  }
]