[
  {
    "Iteration":0,
    "Value":270.3898050975,
    "Agent":"C2D"
  },
  {
    "Iteration":1,
    "Value":523.2026143791,
    "Agent":"C2D"
  },
  {
    "Iteration":2,
    "Value":585.4341736695,
    "Agent":"C2D"
  },
  {
    "Iteration":3,
    "Value":611.5384615385,
    "Agent":"C2D"
  },
  {
    "Iteration":4,
    "Value":669.5286195286,
    "Agent":"C2D"
  },
  {
    "Iteration":5,
    "Value":764.8885350318,
    "Agent":"C2D"
  },
  {
    "Iteration":6,
    "Value":807.3051948052,
    "Agent":"C2D"
  },
  {
    "Iteration":7,
    "Value":855.0,
    "Agent":"C2D"
  },
  {
    "Iteration":8,
    "Value":885.687732342,
    "Agent":"C2D"
  },
  {
    "Iteration":9,
    "Value":1063.2591093117,
    "Agent":"C2D"
  },
  {
    "Iteration":10,
    "Value":1017.4089068826,
    "Agent":"C2D"
  },
  {
    "Iteration":11,
    "Value":1166.0560344828,
    "Agent":"C2D"
  },
  {
    "Iteration":12,
    "Value":1473.9316239316,
    "Agent":"C2D"
  },
  {
    "Iteration":13,
    "Value":1654.8958333333,
    "Agent":"C2D"
  },
  {
    "Iteration":14,
    "Value":2094.2708333333,
    "Agent":"C2D"
  },
  {
    "Iteration":15,
    "Value":2181.1974789916,
    "Agent":"C2D"
  },
  {
    "Iteration":16,
    "Value":2513.9400921659,
    "Agent":"C2D"
  },
  {
    "Iteration":17,
    "Value":2309.388185654,
    "Agent":"C2D"
  },
  {
    "Iteration":18,
    "Value":2882.5342465753,
    "Agent":"C2D"
  },
  {
    "Iteration":19,
    "Value":3084.3434343434,
    "Agent":"C2D"
  },
  {
    "Iteration":20,
    "Value":4162.1761658031,
    "Agent":"C2D"
  },
  {
    "Iteration":21,
    "Value":4278.1767955801,
    "Agent":"C2D"
  },
  {
    "Iteration":22,
    "Value":4453.6982248521,
    "Agent":"C2D"
  },
  {
    "Iteration":23,
    "Value":4713.8081395349,
    "Agent":"C2D"
  },
  {
    "Iteration":24,
    "Value":4807.3099415205,
    "Agent":"C2D"
  },
  {
    "Iteration":25,
    "Value":4805.0561797753,
    "Agent":"C2D"
  },
  {
    "Iteration":26,
    "Value":5164.1768292683,
    "Agent":"C2D"
  },
  {
    "Iteration":27,
    "Value":5883.8028169014,
    "Agent":"C2D"
  },
  {
    "Iteration":28,
    "Value":5420.2830188679,
    "Agent":"C2D"
  },
  {
    "Iteration":29,
    "Value":4772.2222222222,
    "Agent":"C2D"
  },
  {
    "Iteration":30,
    "Value":6433.8,
    "Agent":"C2D"
  },
  {
    "Iteration":31,
    "Value":5933.2116788321,
    "Agent":"C2D"
  },
  {
    "Iteration":32,
    "Value":6137.1428571429,
    "Agent":"C2D"
  },
  {
    "Iteration":33,
    "Value":6670.3007518797,
    "Agent":"C2D"
  },
  {
    "Iteration":34,
    "Value":6434.9264705882,
    "Agent":"C2D"
  },
  {
    "Iteration":35,
    "Value":6373.0215827338,
    "Agent":"C2D"
  },
  {
    "Iteration":36,
    "Value":6446.9424460432,
    "Agent":"C2D"
  },
  {
    "Iteration":37,
    "Value":6355.9602649007,
    "Agent":"C2D"
  },
  {
    "Iteration":38,
    "Value":6085.1265822785,
    "Agent":"C2D"
  },
  {
    "Iteration":39,
    "Value":6699.4897959184,
    "Agent":"C2D"
  },
  {
    "Iteration":40,
    "Value":6918.0743243243,
    "Agent":"C2D"
  },
  {
    "Iteration":41,
    "Value":7306.1594202899,
    "Agent":"C2D"
  },
  {
    "Iteration":42,
    "Value":7597.9927007299,
    "Agent":"C2D"
  },
  {
    "Iteration":43,
    "Value":7213.698630137,
    "Agent":"C2D"
  },
  {
    "Iteration":44,
    "Value":7241.0211267606,
    "Agent":"C2D"
  },
  {
    "Iteration":45,
    "Value":6704.1666666667,
    "Agent":"C2D"
  },
  {
    "Iteration":46,
    "Value":6778.125,
    "Agent":"C2D"
  },
  {
    "Iteration":47,
    "Value":7486.3636363636,
    "Agent":"C2D"
  },
  {
    "Iteration":48,
    "Value":6965.7284768212,
    "Agent":"C2D"
  },
  {
    "Iteration":49,
    "Value":6826.0135135135,
    "Agent":"C2D"
  },
  {
    "Iteration":50,
    "Value":8148.9130434783,
    "Agent":"C2D"
  },
  {
    "Iteration":51,
    "Value":8831.884057971,
    "Agent":"C2D"
  },
  {
    "Iteration":52,
    "Value":7877.2151898734,
    "Agent":"C2D"
  },
  {
    "Iteration":53,
    "Value":8525.3311258278,
    "Agent":"C2D"
  },
  {
    "Iteration":54,
    "Value":9647.1223021583,
    "Agent":"C2D"
  },
  {
    "Iteration":55,
    "Value":9301.3605442177,
    "Agent":"C2D"
  },
  {
    "Iteration":56,
    "Value":9441.2251655629,
    "Agent":"C2D"
  },
  {
    "Iteration":57,
    "Value":9510.6907894737,
    "Agent":"C2D"
  },
  {
    "Iteration":58,
    "Value":9050.6493506493,
    "Agent":"C2D"
  },
  {
    "Iteration":59,
    "Value":9199.0322580645,
    "Agent":"C2D"
  },
  {
    "Iteration":60,
    "Value":9400.3355704698,
    "Agent":"C2D"
  },
  {
    "Iteration":61,
    "Value":11417.4812030075,
    "Agent":"C2D"
  },
  {
    "Iteration":62,
    "Value":11400.9124087591,
    "Agent":"C2D"
  },
  {
    "Iteration":63,
    "Value":11353.6496350365,
    "Agent":"C2D"
  },
  {
    "Iteration":64,
    "Value":10690.4513888889,
    "Agent":"C2D"
  },
  {
    "Iteration":65,
    "Value":12827.6515151515,
    "Agent":"C2D"
  },
  {
    "Iteration":66,
    "Value":12280.7971014493,
    "Agent":"C2D"
  },
  {
    "Iteration":67,
    "Value":12559.0579710145,
    "Agent":"C2D"
  },
  {
    "Iteration":68,
    "Value":12670.6439393939,
    "Agent":"C2D"
  },
  {
    "Iteration":69,
    "Value":12160.0352112676,
    "Agent":"C2D"
  },
  {
    "Iteration":70,
    "Value":13593.1818181818,
    "Agent":"C2D"
  },
  {
    "Iteration":71,
    "Value":14281.3008130081,
    "Agent":"C2D"
  },
  {
    "Iteration":72,
    "Value":12902.962962963,
    "Agent":"C2D"
  },
  {
    "Iteration":73,
    "Value":14283.2627118644,
    "Agent":"C2D"
  },
  {
    "Iteration":74,
    "Value":14549.5901639344,
    "Agent":"C2D"
  },
  {
    "Iteration":75,
    "Value":14313.3064516129,
    "Agent":"C2D"
  },
  {
    "Iteration":76,
    "Value":14528.2258064516,
    "Agent":"C2D"
  },
  {
    "Iteration":77,
    "Value":14273.185483871,
    "Agent":"C2D"
  },
  {
    "Iteration":78,
    "Value":15183.0578512397,
    "Agent":"C2D"
  },
  {
    "Iteration":79,
    "Value":14326.0330578512,
    "Agent":"C2D"
  },
  {
    "Iteration":80,
    "Value":14650.0,
    "Agent":"C2D"
  },
  {
    "Iteration":81,
    "Value":14331.7829457364,
    "Agent":"C2D"
  },
  {
    "Iteration":82,
    "Value":13370.8984375,
    "Agent":"C2D"
  },
  {
    "Iteration":83,
    "Value":14538.2231404959,
    "Agent":"C2D"
  },
  {
    "Iteration":84,
    "Value":14174.4140625,
    "Agent":"C2D"
  },
  {
    "Iteration":85,
    "Value":13764.4444444444,
    "Agent":"C2D"
  },
  {
    "Iteration":86,
    "Value":15191.9491525424,
    "Agent":"C2D"
  },
  {
    "Iteration":87,
    "Value":14884.1101694915,
    "Agent":"C2D"
  },
  {
    "Iteration":88,
    "Value":15975.0,
    "Agent":"C2D"
  },
  {
    "Iteration":89,
    "Value":15832.8947368421,
    "Agent":"C2D"
  },
  {
    "Iteration":90,
    "Value":15258.0578512397,
    "Agent":"C2D"
  },
  {
    "Iteration":91,
    "Value":14934.7916666667,
    "Agent":"C2D"
  },
  {
    "Iteration":92,
    "Value":14443.9024390244,
    "Agent":"C2D"
  },
  {
    "Iteration":93,
    "Value":14478.0737704918,
    "Agent":"C2D"
  },
  {
    "Iteration":94,
    "Value":15501.5086206897,
    "Agent":"C2D"
  },
  {
    "Iteration":95,
    "Value":15684.5132743363,
    "Agent":"C2D"
  },
  {
    "Iteration":96,
    "Value":15928.4403669725,
    "Agent":"C2D"
  },
  {
    "Iteration":97,
    "Value":16307.4074074074,
    "Agent":"C2D"
  },
  {
    "Iteration":98,
    "Value":15286.1344537815,
    "Agent":"C2D"
  },
  {
    "Iteration":99,
    "Value":15177.3504273504,
    "Agent":"C2D"
  },
  {
    "Iteration":100,
    "Value":15734.375,
    "Agent":"C2D"
  },
  {
    "Iteration":101,
    "Value":15464.9553571429,
    "Agent":"C2D"
  },
  {
    "Iteration":102,
    "Value":16538.7614678899,
    "Agent":"C2D"
  },
  {
    "Iteration":103,
    "Value":16265.5660377358,
    "Agent":"C2D"
  },
  {
    "Iteration":104,
    "Value":16449.5283018868,
    "Agent":"C2D"
  },
  {
    "Iteration":105,
    "Value":16175.0,
    "Agent":"C2D"
  },
  {
    "Iteration":106,
    "Value":16608.4158415842,
    "Agent":"C2D"
  },
  {
    "Iteration":107,
    "Value":16297.0297029703,
    "Agent":"C2D"
  },
  {
    "Iteration":108,
    "Value":14927.9411764706,
    "Agent":"C2D"
  },
  {
    "Iteration":109,
    "Value":16049.7685185185,
    "Agent":"C2D"
  },
  {
    "Iteration":110,
    "Value":15876.3274336283,
    "Agent":"C2D"
  },
  {
    "Iteration":111,
    "Value":15322.5,
    "Agent":"C2D"
  },
  {
    "Iteration":112,
    "Value":15766.5966386555,
    "Agent":"C2D"
  },
  {
    "Iteration":113,
    "Value":15530.6722689076,
    "Agent":"C2D"
  },
  {
    "Iteration":114,
    "Value":16379.8672566372,
    "Agent":"C2D"
  },
  {
    "Iteration":115,
    "Value":16177.2522522523,
    "Agent":"C2D"
  },
  {
    "Iteration":116,
    "Value":16148.1818181818,
    "Agent":"C2D"
  },
  {
    "Iteration":117,
    "Value":16123.4649122807,
    "Agent":"C2D"
  },
  {
    "Iteration":118,
    "Value":16904.5454545455,
    "Agent":"C2D"
  },
  {
    "Iteration":119,
    "Value":15912.6146788991,
    "Agent":"C2D"
  },
  {
    "Iteration":120,
    "Value":16325.7075471698,
    "Agent":"C2D"
  },
  {
    "Iteration":121,
    "Value":16246.7889908257,
    "Agent":"C2D"
  },
  {
    "Iteration":122,
    "Value":17292.9292929293,
    "Agent":"C2D"
  },
  {
    "Iteration":123,
    "Value":16551.6666666667,
    "Agent":"C2D"
  },
  {
    "Iteration":124,
    "Value":17017.5480769231,
    "Agent":"C2D"
  },
  {
    "Iteration":125,
    "Value":16746.1165048544,
    "Agent":"C2D"
  },
  {
    "Iteration":126,
    "Value":15789.2543859649,
    "Agent":"C2D"
  },
  {
    "Iteration":127,
    "Value":16439.0186915888,
    "Agent":"C2D"
  },
  {
    "Iteration":128,
    "Value":16690.0485436893,
    "Agent":"C2D"
  },
  {
    "Iteration":129,
    "Value":17272.8723404255,
    "Agent":"C2D"
  },
  {
    "Iteration":130,
    "Value":16699.7619047619,
    "Agent":"C2D"
  },
  {
    "Iteration":131,
    "Value":16332.476635514,
    "Agent":"C2D"
  },
  {
    "Iteration":132,
    "Value":16732.1782178218,
    "Agent":"C2D"
  },
  {
    "Iteration":133,
    "Value":16786.8932038835,
    "Agent":"C2D"
  },
  {
    "Iteration":134,
    "Value":16608.1730769231,
    "Agent":"C2D"
  },
  {
    "Iteration":135,
    "Value":16654.3689320388,
    "Agent":"C2D"
  },
  {
    "Iteration":136,
    "Value":15878.3482142857,
    "Agent":"C2D"
  },
  {
    "Iteration":137,
    "Value":16769.9029126214,
    "Agent":"C2D"
  },
  {
    "Iteration":138,
    "Value":17354.797979798,
    "Agent":"C2D"
  },
  {
    "Iteration":139,
    "Value":15635.8695652174,
    "Agent":"C2D"
  },
  {
    "Iteration":140,
    "Value":16475.7075471698,
    "Agent":"C2D"
  },
  {
    "Iteration":141,
    "Value":16127.2123893805,
    "Agent":"C2D"
  },
  {
    "Iteration":142,
    "Value":16301.1467889908,
    "Agent":"C2D"
  },
  {
    "Iteration":143,
    "Value":16401.1682242991,
    "Agent":"C2D"
  },
  {
    "Iteration":144,
    "Value":16469.0909090909,
    "Agent":"C2D"
  },
  {
    "Iteration":145,
    "Value":16622.8971962617,
    "Agent":"C2D"
  },
  {
    "Iteration":146,
    "Value":16627.5,
    "Agent":"C2D"
  },
  {
    "Iteration":147,
    "Value":16658.5784313725,
    "Agent":"C2D"
  },
  {
    "Iteration":148,
    "Value":16348.8317757009,
    "Agent":"C2D"
  },
  {
    "Iteration":149,
    "Value":16591.2621359223,
    "Agent":"C2D"
  },
  {
    "Iteration":150,
    "Value":15912.3853211009,
    "Agent":"C2D"
  },
  {
    "Iteration":151,
    "Value":15800.8771929825,
    "Agent":"C2D"
  },
  {
    "Iteration":152,
    "Value":17547.3958333333,
    "Agent":"C2D"
  },
  {
    "Iteration":153,
    "Value":16511.9158878505,
    "Agent":"C2D"
  },
  {
    "Iteration":154,
    "Value":16096.7105263158,
    "Agent":"C2D"
  },
  {
    "Iteration":155,
    "Value":16402.8846153846,
    "Agent":"C2D"
  },
  {
    "Iteration":156,
    "Value":16578.0952380952,
    "Agent":"C2D"
  },
  {
    "Iteration":157,
    "Value":16532.3529411765,
    "Agent":"C2D"
  },
  {
    "Iteration":158,
    "Value":17231.3775510204,
    "Agent":"C2D"
  },
  {
    "Iteration":159,
    "Value":16750.0,
    "Agent":"C2D"
  },
  {
    "Iteration":160,
    "Value":17350.7653061224,
    "Agent":"C2D"
  },
  {
    "Iteration":161,
    "Value":17404.0404040404,
    "Agent":"C2D"
  },
  {
    "Iteration":162,
    "Value":16617.7570093458,
    "Agent":"C2D"
  },
  {
    "Iteration":163,
    "Value":17213.1443298969,
    "Agent":"C2D"
  },
  {
    "Iteration":164,
    "Value":16645.0934579439,
    "Agent":"C2D"
  },
  {
    "Iteration":165,
    "Value":17210.101010101,
    "Agent":"C2D"
  },
  {
    "Iteration":166,
    "Value":16928.1862745098,
    "Agent":"C2D"
  },
  {
    "Iteration":167,
    "Value":16049.0909090909,
    "Agent":"C2D"
  },
  {
    "Iteration":168,
    "Value":17143.112244898,
    "Agent":"C2D"
  },
  {
    "Iteration":169,
    "Value":16624.3055555556,
    "Agent":"C2D"
  },
  {
    "Iteration":170,
    "Value":16672.5,
    "Agent":"C2D"
  },
  {
    "Iteration":171,
    "Value":17688.5,
    "Agent":"C2D"
  },
  {
    "Iteration":172,
    "Value":16692.0560747664,
    "Agent":"C2D"
  },
  {
    "Iteration":173,
    "Value":17424.2424242424,
    "Agent":"C2D"
  },
  {
    "Iteration":174,
    "Value":17215.931372549,
    "Agent":"C2D"
  },
  {
    "Iteration":175,
    "Value":16812.5,
    "Agent":"C2D"
  },
  {
    "Iteration":176,
    "Value":17310.25,
    "Agent":"C2D"
  },
  {
    "Iteration":177,
    "Value":17692.1875,
    "Agent":"C2D"
  },
  {
    "Iteration":178,
    "Value":16861.2745098039,
    "Agent":"C2D"
  },
  {
    "Iteration":179,
    "Value":16941.1057692308,
    "Agent":"C2D"
  },
  {
    "Iteration":180,
    "Value":17343.25,
    "Agent":"C2D"
  },
  {
    "Iteration":181,
    "Value":17409.3137254902,
    "Agent":"C2D"
  },
  {
    "Iteration":182,
    "Value":17616.7525773196,
    "Agent":"C2D"
  },
  {
    "Iteration":183,
    "Value":17409.4387755102,
    "Agent":"C2D"
  },
  {
    "Iteration":184,
    "Value":17184.6534653465,
    "Agent":"C2D"
  },
  {
    "Iteration":185,
    "Value":17947.3404255319,
    "Agent":"C2D"
  },
  {
    "Iteration":186,
    "Value":17336.1111111111,
    "Agent":"C2D"
  },
  {
    "Iteration":187,
    "Value":18054.4444444444,
    "Agent":"C2D"
  },
  {
    "Iteration":188,
    "Value":17511.0,
    "Agent":"C2D"
  },
  {
    "Iteration":189,
    "Value":17685.9375,
    "Agent":"C2D"
  },
  {
    "Iteration":190,
    "Value":16979.5,
    "Agent":"C2D"
  },
  {
    "Iteration":191,
    "Value":16745.9905660377,
    "Agent":"C2D"
  },
  {
    "Iteration":192,
    "Value":16447.4299065421,
    "Agent":"C2D"
  },
  {
    "Iteration":193,
    "Value":17209.2233009709,
    "Agent":"C2D"
  },
  {
    "Iteration":194,
    "Value":16763.9705882353,
    "Agent":"C2D"
  },
  {
    "Iteration":195,
    "Value":17253.3505154639,
    "Agent":"C2D"
  },
  {
    "Iteration":196,
    "Value":18386.0465116279,
    "Agent":"C2D"
  },
  {
    "Iteration":197,
    "Value":17475.505050505,
    "Agent":"C2D"
  },
  {
    "Iteration":198,
    "Value":17579.0404040404,
    "Agent":"C2D"
  },
  {
    "Iteration":199,
    "Value":17609.5360824742,
    "Agent":"C2D"
  },
  {
    "Iteration":0,
    "Value":253.8345864662,
    "Agent":"C2D"
  },
  {
    "Iteration":1,
    "Value":517.3701298701,
    "Agent":"C2D"
  },
  {
    "Iteration":2,
    "Value":647.1074380165,
    "Agent":"C2D"
  },
  {
    "Iteration":3,
    "Value":741.642228739,
    "Agent":"C2D"
  },
  {
    "Iteration":4,
    "Value":730.7750759878,
    "Agent":"C2D"
  },
  {
    "Iteration":5,
    "Value":879.1139240506,
    "Agent":"C2D"
  },
  {
    "Iteration":6,
    "Value":1055.7258064516,
    "Agent":"C2D"
  },
  {
    "Iteration":7,
    "Value":1081.3099041534,
    "Agent":"C2D"
  },
  {
    "Iteration":8,
    "Value":1291.2683823529,
    "Agent":"C2D"
  },
  {
    "Iteration":9,
    "Value":1480.1181102362,
    "Agent":"C2D"
  },
  {
    "Iteration":10,
    "Value":1174.7011952191,
    "Agent":"C2D"
  },
  {
    "Iteration":11,
    "Value":1594.693877551,
    "Agent":"C2D"
  },
  {
    "Iteration":12,
    "Value":2355.6352459016,
    "Agent":"C2D"
  },
  {
    "Iteration":13,
    "Value":2640.8139534884,
    "Agent":"C2D"
  },
  {
    "Iteration":14,
    "Value":3425.6313131313,
    "Agent":"C2D"
  },
  {
    "Iteration":15,
    "Value":3054.1666666667,
    "Agent":"C2D"
  },
  {
    "Iteration":16,
    "Value":3505.243902439,
    "Agent":"C2D"
  },
  {
    "Iteration":17,
    "Value":4280.8510638298,
    "Agent":"C2D"
  },
  {
    "Iteration":18,
    "Value":4359.8011363636,
    "Agent":"C2D"
  },
  {
    "Iteration":19,
    "Value":4460.393258427,
    "Agent":"C2D"
  },
  {
    "Iteration":20,
    "Value":5084.6590909091,
    "Agent":"C2D"
  },
  {
    "Iteration":21,
    "Value":5088.4393063584,
    "Agent":"C2D"
  },
  {
    "Iteration":22,
    "Value":5178.2208588957,
    "Agent":"C2D"
  },
  {
    "Iteration":23,
    "Value":5084.9378881988,
    "Agent":"C2D"
  },
  {
    "Iteration":24,
    "Value":5618.4121621622,
    "Agent":"C2D"
  },
  {
    "Iteration":25,
    "Value":5342.3780487805,
    "Agent":"C2D"
  },
  {
    "Iteration":26,
    "Value":5775.9677419355,
    "Agent":"C2D"
  },
  {
    "Iteration":27,
    "Value":5919.5652173913,
    "Agent":"C2D"
  },
  {
    "Iteration":28,
    "Value":6040.2857142857,
    "Agent":"C2D"
  },
  {
    "Iteration":29,
    "Value":6441.4110429448,
    "Agent":"C2D"
  },
  {
    "Iteration":30,
    "Value":5855.6034482759,
    "Agent":"C2D"
  },
  {
    "Iteration":31,
    "Value":6373.4567901235,
    "Agent":"C2D"
  },
  {
    "Iteration":32,
    "Value":6057.9479768786,
    "Agent":"C2D"
  },
  {
    "Iteration":33,
    "Value":7010.3773584906,
    "Agent":"C2D"
  },
  {
    "Iteration":34,
    "Value":7705.9677419355,
    "Agent":"C2D"
  },
  {
    "Iteration":35,
    "Value":7688.2075471698,
    "Agent":"C2D"
  },
  {
    "Iteration":36,
    "Value":6586.8827160494,
    "Agent":"C2D"
  },
  {
    "Iteration":37,
    "Value":7976.8867924528,
    "Agent":"C2D"
  },
  {
    "Iteration":38,
    "Value":7848.9393939394,
    "Agent":"C2D"
  },
  {
    "Iteration":39,
    "Value":9267.4657534247,
    "Agent":"C2D"
  },
  {
    "Iteration":40,
    "Value":9090.8620689655,
    "Agent":"C2D"
  },
  {
    "Iteration":41,
    "Value":10004.8951048951,
    "Agent":"C2D"
  },
  {
    "Iteration":42,
    "Value":9310.3333333333,
    "Agent":"C2D"
  },
  {
    "Iteration":43,
    "Value":11272.027972028,
    "Agent":"C2D"
  },
  {
    "Iteration":44,
    "Value":9985.9060402685,
    "Agent":"C2D"
  },
  {
    "Iteration":45,
    "Value":11283.6330935252,
    "Agent":"C2D"
  },
  {
    "Iteration":46,
    "Value":11616.3669064748,
    "Agent":"C2D"
  },
  {
    "Iteration":47,
    "Value":10565.2317880795,
    "Agent":"C2D"
  },
  {
    "Iteration":48,
    "Value":10820.6666666667,
    "Agent":"C2D"
  },
  {
    "Iteration":49,
    "Value":10375.487012987,
    "Agent":"C2D"
  },
  {
    "Iteration":50,
    "Value":10761.9047619048,
    "Agent":"C2D"
  },
  {
    "Iteration":51,
    "Value":10272.619047619,
    "Agent":"C2D"
  },
  {
    "Iteration":52,
    "Value":12023.5815602837,
    "Agent":"C2D"
  },
  {
    "Iteration":53,
    "Value":12570.2205882353,
    "Agent":"C2D"
  },
  {
    "Iteration":54,
    "Value":12276.6423357664,
    "Agent":"C2D"
  },
  {
    "Iteration":55,
    "Value":11896.5753424658,
    "Agent":"C2D"
  },
  {
    "Iteration":56,
    "Value":10986.2416107383,
    "Agent":"C2D"
  },
  {
    "Iteration":57,
    "Value":12372.8417266187,
    "Agent":"C2D"
  },
  {
    "Iteration":58,
    "Value":13316.2213740458,
    "Agent":"C2D"
  },
  {
    "Iteration":59,
    "Value":13369.6850393701,
    "Agent":"C2D"
  },
  {
    "Iteration":60,
    "Value":13030.8139534884,
    "Agent":"C2D"
  },
  {
    "Iteration":61,
    "Value":13246.992481203,
    "Agent":"C2D"
  },
  {
    "Iteration":62,
    "Value":13792.578125,
    "Agent":"C2D"
  },
  {
    "Iteration":63,
    "Value":13878.7109375,
    "Agent":"C2D"
  },
  {
    "Iteration":64,
    "Value":12547.0802919708,
    "Agent":"C2D"
  },
  {
    "Iteration":65,
    "Value":13546.3178294574,
    "Agent":"C2D"
  },
  {
    "Iteration":66,
    "Value":13816.0852713178,
    "Agent":"C2D"
  },
  {
    "Iteration":67,
    "Value":13863.9112903226,
    "Agent":"C2D"
  },
  {
    "Iteration":68,
    "Value":14035.6,
    "Agent":"C2D"
  },
  {
    "Iteration":69,
    "Value":14395.8333333333,
    "Agent":"C2D"
  },
  {
    "Iteration":70,
    "Value":14264.2,
    "Agent":"C2D"
  },
  {
    "Iteration":71,
    "Value":14015.5241935484,
    "Agent":"C2D"
  },
  {
    "Iteration":72,
    "Value":13986.0687022901,
    "Agent":"C2D"
  },
  {
    "Iteration":73,
    "Value":13550.0,
    "Agent":"C2D"
  },
  {
    "Iteration":74,
    "Value":13792.0542635659,
    "Agent":"C2D"
  },
  {
    "Iteration":75,
    "Value":15077.3913043478,
    "Agent":"C2D"
  },
  {
    "Iteration":76,
    "Value":15394.0170940171,
    "Agent":"C2D"
  },
  {
    "Iteration":77,
    "Value":14709.375,
    "Agent":"C2D"
  },
  {
    "Iteration":78,
    "Value":15362.8318584071,
    "Agent":"C2D"
  },
  {
    "Iteration":79,
    "Value":14675.6048387097,
    "Agent":"C2D"
  },
  {
    "Iteration":80,
    "Value":14547.4206349206,
    "Agent":"C2D"
  },
  {
    "Iteration":81,
    "Value":15007.1120689655,
    "Agent":"C2D"
  },
  {
    "Iteration":82,
    "Value":14934.4537815126,
    "Agent":"C2D"
  },
  {
    "Iteration":83,
    "Value":14555.737704918,
    "Agent":"C2D"
  },
  {
    "Iteration":84,
    "Value":15225.6147540984,
    "Agent":"C2D"
  },
  {
    "Iteration":85,
    "Value":15094.6120689655,
    "Agent":"C2D"
  },
  {
    "Iteration":86,
    "Value":15213.5245901639,
    "Agent":"C2D"
  },
  {
    "Iteration":87,
    "Value":15696.5217391304,
    "Agent":"C2D"
  },
  {
    "Iteration":88,
    "Value":15661.8644067797,
    "Agent":"C2D"
  },
  {
    "Iteration":89,
    "Value":15514.1949152542,
    "Agent":"C2D"
  },
  {
    "Iteration":90,
    "Value":16330.9734513274,
    "Agent":"C2D"
  },
  {
    "Iteration":91,
    "Value":15474.5867768595,
    "Agent":"C2D"
  },
  {
    "Iteration":92,
    "Value":15701.5486725664,
    "Agent":"C2D"
  },
  {
    "Iteration":93,
    "Value":14697.6,
    "Agent":"C2D"
  },
  {
    "Iteration":94,
    "Value":15306.9915254237,
    "Agent":"C2D"
  },
  {
    "Iteration":95,
    "Value":15613.8157894737,
    "Agent":"C2D"
  },
  {
    "Iteration":96,
    "Value":15467.6724137931,
    "Agent":"C2D"
  },
  {
    "Iteration":97,
    "Value":15477.1367521368,
    "Agent":"C2D"
  },
  {
    "Iteration":98,
    "Value":15921.6216216216,
    "Agent":"C2D"
  },
  {
    "Iteration":99,
    "Value":15759.8290598291,
    "Agent":"C2D"
  },
  {
    "Iteration":100,
    "Value":15419.6120689655,
    "Agent":"C2D"
  },
  {
    "Iteration":101,
    "Value":16192.1739130435,
    "Agent":"C2D"
  },
  {
    "Iteration":102,
    "Value":14948.3606557377,
    "Agent":"C2D"
  },
  {
    "Iteration":103,
    "Value":15329.6218487395,
    "Agent":"C2D"
  },
  {
    "Iteration":104,
    "Value":15556.7391304348,
    "Agent":"C2D"
  },
  {
    "Iteration":105,
    "Value":15501.4705882353,
    "Agent":"C2D"
  },
  {
    "Iteration":106,
    "Value":15570.2173913043,
    "Agent":"C2D"
  },
  {
    "Iteration":107,
    "Value":15435.3448275862,
    "Agent":"C2D"
  },
  {
    "Iteration":108,
    "Value":15227.9166666667,
    "Agent":"C2D"
  },
  {
    "Iteration":109,
    "Value":15710.5603448276,
    "Agent":"C2D"
  },
  {
    "Iteration":110,
    "Value":15844.347826087,
    "Agent":"C2D"
  },
  {
    "Iteration":111,
    "Value":16058.185840708,
    "Agent":"C2D"
  },
  {
    "Iteration":112,
    "Value":16107.8828828829,
    "Agent":"C2D"
  },
  {
    "Iteration":113,
    "Value":16300.6944444444,
    "Agent":"C2D"
  },
  {
    "Iteration":114,
    "Value":16731.7757009346,
    "Agent":"C2D"
  },
  {
    "Iteration":115,
    "Value":16918.0693069307,
    "Agent":"C2D"
  },
  {
    "Iteration":116,
    "Value":16918.2692307692,
    "Agent":"C2D"
  },
  {
    "Iteration":117,
    "Value":16712.7358490566,
    "Agent":"C2D"
  },
  {
    "Iteration":118,
    "Value":17252.1428571429,
    "Agent":"C2D"
  },
  {
    "Iteration":119,
    "Value":17628.6057692308,
    "Agent":"C2D"
  },
  {
    "Iteration":120,
    "Value":18260.5670103093,
    "Agent":"C2D"
  },
  {
    "Iteration":121,
    "Value":18376.8617021277,
    "Agent":"C2D"
  },
  {
    "Iteration":122,
    "Value":17304.3269230769,
    "Agent":"C2D"
  },
  {
    "Iteration":123,
    "Value":17139.3867924528,
    "Agent":"C2D"
  },
  {
    "Iteration":124,
    "Value":17049.537037037,
    "Agent":"C2D"
  },
  {
    "Iteration":125,
    "Value":18005.1470588235,
    "Agent":"C2D"
  },
  {
    "Iteration":126,
    "Value":17944.9494949495,
    "Agent":"C2D"
  },
  {
    "Iteration":127,
    "Value":17887.7450980392,
    "Agent":"C2D"
  },
  {
    "Iteration":128,
    "Value":18061.75,
    "Agent":"C2D"
  },
  {
    "Iteration":129,
    "Value":17021.4953271028,
    "Agent":"C2D"
  },
  {
    "Iteration":130,
    "Value":17324.2857142857,
    "Agent":"C2D"
  },
  {
    "Iteration":131,
    "Value":18869.0721649485,
    "Agent":"C2D"
  },
  {
    "Iteration":132,
    "Value":19578.8888888889,
    "Agent":"C2D"
  },
  {
    "Iteration":133,
    "Value":18139.25,
    "Agent":"C2D"
  },
  {
    "Iteration":134,
    "Value":17469.2307692308,
    "Agent":"C2D"
  },
  {
    "Iteration":135,
    "Value":19104.5212765957,
    "Agent":"C2D"
  },
  {
    "Iteration":136,
    "Value":17731.9047619048,
    "Agent":"C2D"
  },
  {
    "Iteration":137,
    "Value":19385.8333333333,
    "Agent":"C2D"
  },
  {
    "Iteration":138,
    "Value":20404.8295454545,
    "Agent":"C2D"
  },
  {
    "Iteration":139,
    "Value":18475.2551020408,
    "Agent":"C2D"
  },
  {
    "Iteration":140,
    "Value":20638.8235294118,
    "Agent":"C2D"
  },
  {
    "Iteration":141,
    "Value":20663.7931034483,
    "Agent":"C2D"
  },
  {
    "Iteration":142,
    "Value":20929.3604651163,
    "Agent":"C2D"
  },
  {
    "Iteration":143,
    "Value":18198.5148514851,
    "Agent":"C2D"
  },
  {
    "Iteration":144,
    "Value":18664.7368421053,
    "Agent":"C2D"
  },
  {
    "Iteration":145,
    "Value":19292.7419354839,
    "Agent":"C2D"
  },
  {
    "Iteration":146,
    "Value":20244.3181818182,
    "Agent":"C2D"
  },
  {
    "Iteration":147,
    "Value":19024.7282608696,
    "Agent":"C2D"
  },
  {
    "Iteration":148,
    "Value":19095.8333333333,
    "Agent":"C2D"
  },
  {
    "Iteration":149,
    "Value":19816.9444444444,
    "Agent":"C2D"
  },
  {
    "Iteration":150,
    "Value":20067.3295454545,
    "Agent":"C2D"
  },
  {
    "Iteration":151,
    "Value":20299.7191011236,
    "Agent":"C2D"
  },
  {
    "Iteration":152,
    "Value":19092.7419354839,
    "Agent":"C2D"
  },
  {
    "Iteration":153,
    "Value":19676.3586956522,
    "Agent":"C2D"
  },
  {
    "Iteration":154,
    "Value":19348.6559139785,
    "Agent":"C2D"
  },
  {
    "Iteration":155,
    "Value":19893.5393258427,
    "Agent":"C2D"
  },
  {
    "Iteration":156,
    "Value":19638.4408602151,
    "Agent":"C2D"
  },
  {
    "Iteration":157,
    "Value":19713.0319148936,
    "Agent":"C2D"
  },
  {
    "Iteration":158,
    "Value":19998.3146067416,
    "Agent":"C2D"
  },
  {
    "Iteration":159,
    "Value":20710.2941176471,
    "Agent":"C2D"
  },
  {
    "Iteration":160,
    "Value":20448.3333333333,
    "Agent":"C2D"
  },
  {
    "Iteration":161,
    "Value":19179.2553191489,
    "Agent":"C2D"
  },
  {
    "Iteration":162,
    "Value":20391.6666666667,
    "Agent":"C2D"
  },
  {
    "Iteration":163,
    "Value":20386.8131868132,
    "Agent":"C2D"
  },
  {
    "Iteration":164,
    "Value":19796.2365591398,
    "Agent":"C2D"
  },
  {
    "Iteration":165,
    "Value":20466.2921348315,
    "Agent":"C2D"
  },
  {
    "Iteration":166,
    "Value":19642.2680412371,
    "Agent":"C2D"
  },
  {
    "Iteration":167,
    "Value":19697.9166666667,
    "Agent":"C2D"
  },
  {
    "Iteration":168,
    "Value":21833.1325301205,
    "Agent":"C2D"
  },
  {
    "Iteration":169,
    "Value":20335.5555555556,
    "Agent":"C2D"
  },
  {
    "Iteration":170,
    "Value":20280.6179775281,
    "Agent":"C2D"
  },
  {
    "Iteration":171,
    "Value":21146.7261904762,
    "Agent":"C2D"
  },
  {
    "Iteration":172,
    "Value":20467.8977272727,
    "Agent":"C2D"
  },
  {
    "Iteration":173,
    "Value":20567.1348314607,
    "Agent":"C2D"
  },
  {
    "Iteration":174,
    "Value":21490.4069767442,
    "Agent":"C2D"
  },
  {
    "Iteration":175,
    "Value":22416.9642857143,
    "Agent":"C2D"
  },
  {
    "Iteration":176,
    "Value":21148.5465116279,
    "Agent":"C2D"
  },
  {
    "Iteration":177,
    "Value":20198.8888888889,
    "Agent":"C2D"
  },
  {
    "Iteration":178,
    "Value":19499.1847826087,
    "Agent":"C2D"
  },
  {
    "Iteration":179,
    "Value":22354.2682926829,
    "Agent":"C2D"
  },
  {
    "Iteration":180,
    "Value":21932.2289156627,
    "Agent":"C2D"
  },
  {
    "Iteration":181,
    "Value":22328.0864197531,
    "Agent":"C2D"
  },
  {
    "Iteration":182,
    "Value":19377.0408163265,
    "Agent":"C2D"
  },
  {
    "Iteration":183,
    "Value":20330.9659090909,
    "Agent":"C2D"
  },
  {
    "Iteration":184,
    "Value":20537.2159090909,
    "Agent":"C2D"
  },
  {
    "Iteration":185,
    "Value":21251.1627906977,
    "Agent":"C2D"
  },
  {
    "Iteration":186,
    "Value":20662.5,
    "Agent":"C2D"
  },
  {
    "Iteration":187,
    "Value":20946.2643678161,
    "Agent":"C2D"
  },
  {
    "Iteration":188,
    "Value":20890.3409090909,
    "Agent":"C2D"
  },
  {
    "Iteration":189,
    "Value":20225.2688172043,
    "Agent":"C2D"
  },
  {
    "Iteration":190,
    "Value":21117.2413793103,
    "Agent":"C2D"
  },
  {
    "Iteration":191,
    "Value":21810.0609756098,
    "Agent":"C2D"
  },
  {
    "Iteration":192,
    "Value":19560.6770833333,
    "Agent":"C2D"
  },
  {
    "Iteration":193,
    "Value":20833.0459770115,
    "Agent":"C2D"
  },
  {
    "Iteration":194,
    "Value":21525.9036144578,
    "Agent":"C2D"
  },
  {
    "Iteration":195,
    "Value":21667.1686746988,
    "Agent":"C2D"
  },
  {
    "Iteration":196,
    "Value":22535.4430379747,
    "Agent":"C2D"
  },
  {
    "Iteration":197,
    "Value":21255.2941176471,
    "Agent":"C2D"
  },
  {
    "Iteration":198,
    "Value":21138.7931034483,
    "Agent":"C2D"
  },
  {
    "Iteration":199,
    "Value":20686.4942528736,
    "Agent":"C2D"
  },
  {
    "Iteration":0,
    "Value":255.8692421991,
    "Agent":"C2D"
  },
  {
    "Iteration":1,
    "Value":505.3278688525,
    "Agent":"C2D"
  },
  {
    "Iteration":2,
    "Value":722.7791878173,
    "Agent":"C2D"
  },
  {
    "Iteration":3,
    "Value":832.3224852071,
    "Agent":"C2D"
  },
  {
    "Iteration":4,
    "Value":1005.9309309309,
    "Agent":"C2D"
  },
  {
    "Iteration":5,
    "Value":849.6978851964,
    "Agent":"C2D"
  },
  {
    "Iteration":6,
    "Value":871.6237942122,
    "Agent":"C2D"
  },
  {
    "Iteration":7,
    "Value":1242.3986486486,
    "Agent":"C2D"
  },
  {
    "Iteration":8,
    "Value":1016.6083916084,
    "Agent":"C2D"
  },
  {
    "Iteration":9,
    "Value":1345.6395348837,
    "Agent":"C2D"
  },
  {
    "Iteration":10,
    "Value":1268.5897435897,
    "Agent":"C2D"
  },
  {
    "Iteration":11,
    "Value":1850.7201646091,
    "Agent":"C2D"
  },
  {
    "Iteration":12,
    "Value":2111.6452991453,
    "Agent":"C2D"
  },
  {
    "Iteration":13,
    "Value":2618.6046511628,
    "Agent":"C2D"
  },
  {
    "Iteration":14,
    "Value":2669.6759259259,
    "Agent":"C2D"
  },
  {
    "Iteration":15,
    "Value":2505.7522123894,
    "Agent":"C2D"
  },
  {
    "Iteration":16,
    "Value":3771.3768115942,
    "Agent":"C2D"
  },
  {
    "Iteration":17,
    "Value":4106.4070351759,
    "Agent":"C2D"
  },
  {
    "Iteration":18,
    "Value":4129.7297297297,
    "Agent":"C2D"
  },
  {
    "Iteration":19,
    "Value":3983.0310880829,
    "Agent":"C2D"
  },
  {
    "Iteration":20,
    "Value":3767.6701570681,
    "Agent":"C2D"
  },
  {
    "Iteration":21,
    "Value":4253.0555555556,
    "Agent":"C2D"
  },
  {
    "Iteration":22,
    "Value":4254.7043010753,
    "Agent":"C2D"
  },
  {
    "Iteration":23,
    "Value":4869.8529411765,
    "Agent":"C2D"
  },
  {
    "Iteration":24,
    "Value":4589.5833333333,
    "Agent":"C2D"
  },
  {
    "Iteration":25,
    "Value":4400.1396648045,
    "Agent":"C2D"
  },
  {
    "Iteration":26,
    "Value":5453.7974683544,
    "Agent":"C2D"
  },
  {
    "Iteration":27,
    "Value":5511.7924528302,
    "Agent":"C2D"
  },
  {
    "Iteration":28,
    "Value":5586.25,
    "Agent":"C2D"
  },
  {
    "Iteration":29,
    "Value":5526.4880952381,
    "Agent":"C2D"
  },
  {
    "Iteration":30,
    "Value":6280.2631578947,
    "Agent":"C2D"
  },
  {
    "Iteration":31,
    "Value":5617.7215189873,
    "Agent":"C2D"
  },
  {
    "Iteration":32,
    "Value":6006.2091503268,
    "Agent":"C2D"
  },
  {
    "Iteration":33,
    "Value":5675.1552795031,
    "Agent":"C2D"
  },
  {
    "Iteration":34,
    "Value":6267.8571428571,
    "Agent":"C2D"
  },
  {
    "Iteration":35,
    "Value":6545.8064516129,
    "Agent":"C2D"
  },
  {
    "Iteration":36,
    "Value":6266.8238993711,
    "Agent":"C2D"
  },
  {
    "Iteration":37,
    "Value":7050.8278145695,
    "Agent":"C2D"
  },
  {
    "Iteration":38,
    "Value":7105.7189542484,
    "Agent":"C2D"
  },
  {
    "Iteration":39,
    "Value":7171.2585034014,
    "Agent":"C2D"
  },
  {
    "Iteration":40,
    "Value":7511.9281045752,
    "Agent":"C2D"
  },
  {
    "Iteration":41,
    "Value":8132.8231292517,
    "Agent":"C2D"
  },
  {
    "Iteration":42,
    "Value":7527.2875816993,
    "Agent":"C2D"
  },
  {
    "Iteration":43,
    "Value":8151.1904761905,
    "Agent":"C2D"
  },
  {
    "Iteration":44,
    "Value":8463.0952380952,
    "Agent":"C2D"
  },
  {
    "Iteration":45,
    "Value":7776.226993865,
    "Agent":"C2D"
  },
  {
    "Iteration":46,
    "Value":9114.2123287671,
    "Agent":"C2D"
  },
  {
    "Iteration":47,
    "Value":10579.4444444444,
    "Agent":"C2D"
  },
  {
    "Iteration":48,
    "Value":9076.1513157895,
    "Agent":"C2D"
  },
  {
    "Iteration":49,
    "Value":9536.8150684932,
    "Agent":"C2D"
  },
  {
    "Iteration":50,
    "Value":9703.4013605442,
    "Agent":"C2D"
  },
  {
    "Iteration":51,
    "Value":10248.8970588235,
    "Agent":"C2D"
  },
  {
    "Iteration":52,
    "Value":11042.9924242424,
    "Agent":"C2D"
  },
  {
    "Iteration":53,
    "Value":11006.954887218,
    "Agent":"C2D"
  },
  {
    "Iteration":54,
    "Value":11669.1729323308,
    "Agent":"C2D"
  },
  {
    "Iteration":55,
    "Value":10143.9935064935,
    "Agent":"C2D"
  },
  {
    "Iteration":56,
    "Value":11655.1526717557,
    "Agent":"C2D"
  },
  {
    "Iteration":57,
    "Value":11625.3759398496,
    "Agent":"C2D"
  },
  {
    "Iteration":58,
    "Value":10716.7832167832,
    "Agent":"C2D"
  },
  {
    "Iteration":59,
    "Value":10918.0555555556,
    "Agent":"C2D"
  },
  {
    "Iteration":60,
    "Value":9918.0921052632,
    "Agent":"C2D"
  },
  {
    "Iteration":61,
    "Value":10074.0066225166,
    "Agent":"C2D"
  },
  {
    "Iteration":62,
    "Value":11592.0955882353,
    "Agent":"C2D"
  },
  {
    "Iteration":63,
    "Value":10795.8609271523,
    "Agent":"C2D"
  },
  {
    "Iteration":64,
    "Value":10349.8376623377,
    "Agent":"C2D"
  },
  {
    "Iteration":65,
    "Value":11736.9718309859,
    "Agent":"C2D"
  },
  {
    "Iteration":66,
    "Value":11980.6896551724,
    "Agent":"C2D"
  },
  {
    "Iteration":67,
    "Value":12603.5447761194,
    "Agent":"C2D"
  },
  {
    "Iteration":68,
    "Value":12322.9310344828,
    "Agent":"C2D"
  },
  {
    "Iteration":69,
    "Value":12568.5251798561,
    "Agent":"C2D"
  },
  {
    "Iteration":70,
    "Value":13413.358778626,
    "Agent":"C2D"
  },
  {
    "Iteration":71,
    "Value":13675.5813953488,
    "Agent":"C2D"
  },
  {
    "Iteration":72,
    "Value":13791.3461538462,
    "Agent":"C2D"
  },
  {
    "Iteration":73,
    "Value":14129.1015625,
    "Agent":"C2D"
  },
  {
    "Iteration":74,
    "Value":13169.2028985507,
    "Agent":"C2D"
  },
  {
    "Iteration":75,
    "Value":13141.1231884058,
    "Agent":"C2D"
  },
  {
    "Iteration":76,
    "Value":13898.4848484848,
    "Agent":"C2D"
  },
  {
    "Iteration":77,
    "Value":14206.3953488372,
    "Agent":"C2D"
  },
  {
    "Iteration":78,
    "Value":13578.3582089552,
    "Agent":"C2D"
  },
  {
    "Iteration":79,
    "Value":14282.5757575758,
    "Agent":"C2D"
  },
  {
    "Iteration":80,
    "Value":13227.4074074074,
    "Agent":"C2D"
  },
  {
    "Iteration":81,
    "Value":13613.503649635,
    "Agent":"C2D"
  },
  {
    "Iteration":82,
    "Value":14173.4962406015,
    "Agent":"C2D"
  },
  {
    "Iteration":83,
    "Value":14556.015037594,
    "Agent":"C2D"
  },
  {
    "Iteration":84,
    "Value":14543.3823529412,
    "Agent":"C2D"
  },
  {
    "Iteration":85,
    "Value":14587.1323529412,
    "Agent":"C2D"
  },
  {
    "Iteration":86,
    "Value":14287.213740458,
    "Agent":"C2D"
  },
  {
    "Iteration":87,
    "Value":15721.4583333333,
    "Agent":"C2D"
  },
  {
    "Iteration":88,
    "Value":14886.7424242424,
    "Agent":"C2D"
  },
  {
    "Iteration":89,
    "Value":14727.2727272727,
    "Agent":"C2D"
  },
  {
    "Iteration":90,
    "Value":14890.9615384615,
    "Agent":"C2D"
  },
  {
    "Iteration":91,
    "Value":15475.2100840336,
    "Agent":"C2D"
  },
  {
    "Iteration":92,
    "Value":15363.75,
    "Agent":"C2D"
  },
  {
    "Iteration":93,
    "Value":15051.2295081967,
    "Agent":"C2D"
  },
  {
    "Iteration":94,
    "Value":15331.762295082,
    "Agent":"C2D"
  },
  {
    "Iteration":95,
    "Value":15312.8048780488,
    "Agent":"C2D"
  },
  {
    "Iteration":96,
    "Value":15516.6666666667,
    "Agent":"C2D"
  },
  {
    "Iteration":97,
    "Value":15362.5,
    "Agent":"C2D"
  },
  {
    "Iteration":98,
    "Value":15400.9398496241,
    "Agent":"C2D"
  },
  {
    "Iteration":99,
    "Value":15559.756097561,
    "Agent":"C2D"
  },
  {
    "Iteration":100,
    "Value":17099.0384615385,
    "Agent":"C2D"
  },
  {
    "Iteration":101,
    "Value":15917.4369747899,
    "Agent":"C2D"
  },
  {
    "Iteration":102,
    "Value":15990.5701754386,
    "Agent":"C2D"
  },
  {
    "Iteration":103,
    "Value":17274.0990990991,
    "Agent":"C2D"
  },
  {
    "Iteration":104,
    "Value":16068.1034482759,
    "Agent":"C2D"
  },
  {
    "Iteration":105,
    "Value":16566.3043478261,
    "Agent":"C2D"
  },
  {
    "Iteration":106,
    "Value":16046.0743801653,
    "Agent":"C2D"
  },
  {
    "Iteration":107,
    "Value":15657.2916666667,
    "Agent":"C2D"
  },
  {
    "Iteration":108,
    "Value":16845.5752212389,
    "Agent":"C2D"
  },
  {
    "Iteration":109,
    "Value":17120.9821428571,
    "Agent":"C2D"
  },
  {
    "Iteration":110,
    "Value":18096.6019417476,
    "Agent":"C2D"
  },
  {
    "Iteration":111,
    "Value":17701.7156862745,
    "Agent":"C2D"
  },
  {
    "Iteration":112,
    "Value":17851.4423076923,
    "Agent":"C2D"
  },
  {
    "Iteration":113,
    "Value":17123.3944954128,
    "Agent":"C2D"
  },
  {
    "Iteration":114,
    "Value":17827.4038461538,
    "Agent":"C2D"
  },
  {
    "Iteration":115,
    "Value":17750.4545454545,
    "Agent":"C2D"
  },
  {
    "Iteration":116,
    "Value":16814.347826087,
    "Agent":"C2D"
  },
  {
    "Iteration":117,
    "Value":16113.2478632479,
    "Agent":"C2D"
  },
  {
    "Iteration":118,
    "Value":18186.4285714286,
    "Agent":"C2D"
  },
  {
    "Iteration":119,
    "Value":17993.6274509804,
    "Agent":"C2D"
  },
  {
    "Iteration":120,
    "Value":16916.2162162162,
    "Agent":"C2D"
  },
  {
    "Iteration":121,
    "Value":16556.6371681416,
    "Agent":"C2D"
  },
  {
    "Iteration":122,
    "Value":17373.8532110092,
    "Agent":"C2D"
  },
  {
    "Iteration":123,
    "Value":17281.1926605505,
    "Agent":"C2D"
  },
  {
    "Iteration":124,
    "Value":17734.5238095238,
    "Agent":"C2D"
  },
  {
    "Iteration":125,
    "Value":18223.3009708738,
    "Agent":"C2D"
  },
  {
    "Iteration":126,
    "Value":18201.6666666667,
    "Agent":"C2D"
  },
  {
    "Iteration":127,
    "Value":17298.623853211,
    "Agent":"C2D"
  },
  {
    "Iteration":128,
    "Value":19015.306122449,
    "Agent":"C2D"
  },
  {
    "Iteration":129,
    "Value":19052.0,
    "Agent":"C2D"
  },
  {
    "Iteration":130,
    "Value":18534.7087378641,
    "Agent":"C2D"
  },
  {
    "Iteration":131,
    "Value":18556.1881188119,
    "Agent":"C2D"
  },
  {
    "Iteration":132,
    "Value":19515.5263157895,
    "Agent":"C2D"
  },
  {
    "Iteration":133,
    "Value":18447.1153846154,
    "Agent":"C2D"
  },
  {
    "Iteration":134,
    "Value":19255.46875,
    "Agent":"C2D"
  },
  {
    "Iteration":135,
    "Value":17453.5714285714,
    "Agent":"C2D"
  },
  {
    "Iteration":136,
    "Value":18889.8514851485,
    "Agent":"C2D"
  },
  {
    "Iteration":137,
    "Value":18375.4761904762,
    "Agent":"C2D"
  },
  {
    "Iteration":138,
    "Value":18198.3009708738,
    "Agent":"C2D"
  },
  {
    "Iteration":139,
    "Value":19393.6224489796,
    "Agent":"C2D"
  },
  {
    "Iteration":140,
    "Value":20046.2765957447,
    "Agent":"C2D"
  },
  {
    "Iteration":141,
    "Value":19950.5208333333,
    "Agent":"C2D"
  },
  {
    "Iteration":142,
    "Value":19420.297029703,
    "Agent":"C2D"
  },
  {
    "Iteration":143,
    "Value":18776.2376237624,
    "Agent":"C2D"
  },
  {
    "Iteration":144,
    "Value":18945.297029703,
    "Agent":"C2D"
  },
  {
    "Iteration":145,
    "Value":19996.6494845361,
    "Agent":"C2D"
  },
  {
    "Iteration":146,
    "Value":18748.25,
    "Agent":"C2D"
  },
  {
    "Iteration":147,
    "Value":19534.375,
    "Agent":"C2D"
  },
  {
    "Iteration":148,
    "Value":19536.3157894737,
    "Agent":"C2D"
  },
  {
    "Iteration":149,
    "Value":19219.3298969072,
    "Agent":"C2D"
  },
  {
    "Iteration":150,
    "Value":20517.4157303371,
    "Agent":"C2D"
  },
  {
    "Iteration":151,
    "Value":19976.0869565217,
    "Agent":"C2D"
  },
  {
    "Iteration":152,
    "Value":19273.7373737374,
    "Agent":"C2D"
  },
  {
    "Iteration":153,
    "Value":20645.2777777778,
    "Agent":"C2D"
  },
  {
    "Iteration":154,
    "Value":19059.595959596,
    "Agent":"C2D"
  },
  {
    "Iteration":155,
    "Value":20523.0555555556,
    "Agent":"C2D"
  },
  {
    "Iteration":156,
    "Value":20309.0659340659,
    "Agent":"C2D"
  },
  {
    "Iteration":157,
    "Value":18931.4356435644,
    "Agent":"C2D"
  },
  {
    "Iteration":158,
    "Value":18973.7113402062,
    "Agent":"C2D"
  },
  {
    "Iteration":159,
    "Value":20378.2967032967,
    "Agent":"C2D"
  },
  {
    "Iteration":160,
    "Value":20254.5698924731,
    "Agent":"C2D"
  },
  {
    "Iteration":161,
    "Value":19033.5858585859,
    "Agent":"C2D"
  },
  {
    "Iteration":162,
    "Value":19951.0526315789,
    "Agent":"C2D"
  },
  {
    "Iteration":163,
    "Value":19996.8421052632,
    "Agent":"C2D"
  },
  {
    "Iteration":164,
    "Value":19903.6458333333,
    "Agent":"C2D"
  },
  {
    "Iteration":165,
    "Value":20492.5,
    "Agent":"C2D"
  },
  {
    "Iteration":166,
    "Value":20923.8764044944,
    "Agent":"C2D"
  },
  {
    "Iteration":167,
    "Value":21062.9310344828,
    "Agent":"C2D"
  },
  {
    "Iteration":168,
    "Value":19276.5306122449,
    "Agent":"C2D"
  },
  {
    "Iteration":169,
    "Value":19388.25,
    "Agent":"C2D"
  },
  {
    "Iteration":170,
    "Value":20326.8617021277,
    "Agent":"C2D"
  },
  {
    "Iteration":171,
    "Value":20491.935483871,
    "Agent":"C2D"
  },
  {
    "Iteration":172,
    "Value":20739.7727272727,
    "Agent":"C2D"
  },
  {
    "Iteration":173,
    "Value":20293.2065217391,
    "Agent":"C2D"
  },
  {
    "Iteration":174,
    "Value":21012.2159090909,
    "Agent":"C2D"
  },
  {
    "Iteration":175,
    "Value":20842.032967033,
    "Agent":"C2D"
  },
  {
    "Iteration":176,
    "Value":20801.4204545455,
    "Agent":"C2D"
  },
  {
    "Iteration":177,
    "Value":20576.0989010989,
    "Agent":"C2D"
  },
  {
    "Iteration":178,
    "Value":20564.010989011,
    "Agent":"C2D"
  },
  {
    "Iteration":179,
    "Value":19336.0215053763,
    "Agent":"C2D"
  },
  {
    "Iteration":180,
    "Value":20801.7045454545,
    "Agent":"C2D"
  },
  {
    "Iteration":181,
    "Value":21732.4712643678,
    "Agent":"C2D"
  },
  {
    "Iteration":182,
    "Value":20438.8888888889,
    "Agent":"C2D"
  },
  {
    "Iteration":183,
    "Value":21549.7126436782,
    "Agent":"C2D"
  },
  {
    "Iteration":184,
    "Value":21365.625,
    "Agent":"C2D"
  },
  {
    "Iteration":185,
    "Value":21383.2386363636,
    "Agent":"C2D"
  },
  {
    "Iteration":186,
    "Value":20850.2808988764,
    "Agent":"C2D"
  },
  {
    "Iteration":187,
    "Value":23095.5696202532,
    "Agent":"C2D"
  },
  {
    "Iteration":188,
    "Value":22565.243902439,
    "Agent":"C2D"
  },
  {
    "Iteration":189,
    "Value":22321.130952381,
    "Agent":"C2D"
  },
  {
    "Iteration":190,
    "Value":20366.5760869565,
    "Agent":"C2D"
  },
  {
    "Iteration":191,
    "Value":20110.5670103093,
    "Agent":"C2D"
  },
  {
    "Iteration":192,
    "Value":21865.8045977011,
    "Agent":"C2D"
  },
  {
    "Iteration":193,
    "Value":23357.7160493827,
    "Agent":"C2D"
  },
  {
    "Iteration":194,
    "Value":20579.2134831461,
    "Agent":"C2D"
  },
  {
    "Iteration":195,
    "Value":21627.0348837209,
    "Agent":"C2D"
  },
  {
    "Iteration":196,
    "Value":22142.8571428571,
    "Agent":"C2D"
  },
  {
    "Iteration":197,
    "Value":21715.0568181818,
    "Agent":"C2D"
  },
  {
    "Iteration":198,
    "Value":23275.0,
    "Agent":"C2D"
  },
  {
    "Iteration":199,
    "Value":22109.9431818182,
    "Agent":"C2D"
  }
]